[
  {
    "slug": "toyota-kowloon-bay-showroom",
    "name": "Toyota Kowloon Bay Showroom",
    "category": "car",
    "subcategory": "car-showroom",
    "area": "kowloon-bay",
    "address": "G/F, Centre Parc, 11 Sheung Yuet Road, Kowloon Bay",
    "phone": "+85228847999",
    "website": "https://www.toyota.com.hk/en/our-locations/",
    "hours": "月〜土 9:00〜19:00、日・祝 10:00〜19:00",
    "price_range": "車両価格による",
    "tags": [
      "トヨタ",
      "新車",
      "試乗",
      "日本車",
      "九龍湾"
    ],
    "description": "九龍湾のフラッグシップショールームでトヨタの最新モデルを展示。日本語対応スタッフあり。",
    "detail": "トヨタ香港の旗艦ショールームで、九龍湾のCentre Parcに位置する。最新のSUV・セダン・ハイブリッド・電気自動車（BZ4X等）の試乗・購入相談が可能。日本語対応スタッフが在籍しており、在住日本人の車両購入にも対応。香港では右ハンドル・左側通行のため、日本からの帰任後も違和感なく運転できる。MTR九龍湾駅からも近いアクセスしやすい立地。",
    "menu": null,
    "source_url": "https://www.toyota.com.hk/en/our-locations/",
    "source": "web_search",
    "status": "unverified",
    "ai_reviewed": true,
    "last_verified": "2026-04-05"
  },
  {
    "slug": "toyota-wan-chai-showroom",
    "name": "Toyota Wan Chai Showroom",
    "category": "car",
    "subcategory": "car-showroom",
    "area": "wan-chai",
    "address": "Shop A, G/F, Harcourt House, 39 Gloucester Road, Wan Chai",
    "phone": "+85228866188",
    "website": "https://www.toyota.com.hk/en/our-locations/",
    "hours": "月〜土 9:00〜19:00、日・祝 10:00〜19:00",
    "price_range": "車両価格による",
    "tags": [
      "トヨタ",
      "新車",
      "試乗",
      "日本車",
      "湾仔"
    ],
    "description": "湾仔のGloucester Road沿いにあるトヨタのショールーム。中環・湾仔エリアからアクセスしやすい。",
    "detail": "トヨタ香港の湾仔ショールームはGloucester Road 39号のHarcourt HouseG/Fに位置する。湾仔・中環のビジネス街に近く、会社帰りや週末に立ち寄りやすい立地。最新モデルの展示・試乗・購入手続きが可能。ハイブリッド車・電気自動車にも力を入れており、環境意識の高いユーザーにも対応。香港での車両購入・保険・登録手続きのサポートも充実。",
    "menu": null,
    "source_url": "https://www.toyota.com.hk/en/our-locations/",
    "source": "web_search",
    "status": "unverified",
    "ai_reviewed": true,
    "last_verified": "2026-04-05"
  },
  {
    "slug": "toyota-north-point-service-centre",
    "name": "Toyota North Point Service Centre",
    "category": "car",
    "subcategory": "car-service",
    "area": "north-point",
    "address": "Block B & C, G/F, Seaview Estate, 2-8 Watson Road, North Point",
    "phone": "+85228801555",
    "website": "https://www.toyota.com.hk/en/our-locations/",
    "hours": "月〜金 7:45〜19:00、土 7:45〜18:00",
    "price_range": "サービス内容による",
    "tags": [
      "トヨタ",
      "車検",
      "メンテナンス",
      "修理",
      "北角"
    ],
    "description": "北角にあるトヨタの公式サービスセンター。定期点検・車検・修理に対応。香港島北部からアクセスしやすい。",
    "detail": "トヨタ香港の公式メカニカルサービスセンター（北角）。Watson Road沿いのSeaview Estate G/Fに位置し、香港島北部エリアの車オーナーに便利。定期点検・オイル交換・タイヤ交換・車検・一般修理に対応する公式サービス拠点。日本車であるトヨタの純正部品を使用したメンテナンスが受けられる。在住日本人がトヨタ車を所有する場合の信頼できるサービス先として推奨される。",
    "menu": null,
    "source_url": "https://www.toyota.com.hk/en/our-locations/",
    "source": "web_search",
    "status": "unverified",
    "ai_reviewed": true,
    "last_verified": "2026-04-05"
  },
  {
    "slug": "toyota-sha-tin-service-centre",
    "name": "Toyota Sha Tin Service Centre",
    "category": "car",
    "subcategory": "car-service",
    "area": "sha-tin",
    "address": "2/F, Topsail Plaza, 11 On Sum Street, Siu Lek Yuen, Sha Tin",
    "phone": "+85228255222",
    "website": "https://www.toyota.com.hk/en/our-locations/",
    "hours": "月〜金 7:45〜19:00、土 7:45〜18:00",
    "price_range": "サービス内容による",
    "tags": [
      "トヨタ",
      "車検",
      "メンテナンス",
      "板金",
      "沙田"
    ],
    "description": "沙田にあるトヨタの公式サービスセンター。整備（メカニカル）と板金・塗装（ボディ＆ペイント）の両方に対応。",
    "detail": "トヨタ香港の沙田（Sha Tin）サービスセンターは、Topsail Plaza 2Fに位置する。沙田は新界エリアの主要な住宅都市で、日本人ファミリーの居住者も多い。メカニカル整備だけでなくボディ＆ペイント（板金・塗装）にも対応する充実した設備を持つ。交通事故後の修理・タッチアップ・定期点検・車検まで幅広いサービスを提供。",
    "menu": null,
    "source_url": "https://www.toyota.com.hk/en/our-locations/",
    "source": "web_search",
    "status": "unverified",
    "ai_reviewed": true,
    "last_verified": "2026-04-05"
  },
  {
    "slug": "toyota-kowloon-bay-service-centre",
    "name": "Toyota Kowloon Bay Service Centre",
    "category": "car",
    "subcategory": "car-service",
    "area": "kowloon-bay",
    "address": "G/F, Jing Hin Industrial Building, 5 Wang Kee Street, Kowloon Bay",
    "phone": "+85228217321",
    "website": "https://www.toyota.com.hk/en/our-locations/",
    "hours": "月〜金 7:45〜19:00、土 7:45〜18:00",
    "price_range": "サービス内容による",
    "tags": [
      "トヨタ",
      "車検",
      "メンテナンス",
      "九龍湾"
    ],
    "description": "九龍湾のJing Hin工業ビルにあるトヨタ公式サービスセンター。メカニカル整備専門。",
    "detail": "トヨタ香港の九龍湾サービスセンターはWang Kee Street 5号のJing Hin Industrial Building G/Fに位置する。九龍湾は工業・商業エリアとして発展しており、近隣に住む・働くトヨタオーナーのメンテナンス拠点として機能。定期点検・オイル交換・部品交換・車検に対応。フラッグシップショールームと同エリアにあるため、購入・アフターサービスの一貫した対応が可能。",
    "menu": null,
    "source_url": "https://www.toyota.com.hk/en/our-locations/",
    "source": "web_search",
    "status": "unverified",
    "ai_reviewed": true,
    "last_verified": "2026-04-05"
  },
  {
    "slug": "honda-wan-chai-showroom",
    "name": "Honda Wan Chai Showroom",
    "category": "car",
    "subcategory": "car-showroom",
    "area": "wan-chai",
    "address": "Shop C, G/F, MassMutual Tower, 38 Gloucester Road, Wan Chai",
    "phone": null,
    "website": "https://www.honda.com.hk",
    "hours": "月〜土 9:00〜19:00、日・祝 10:00〜19:00",
    "price_range": "車両価格による",
    "tags": [
      "ホンダ",
      "新車",
      "試乗",
      "日本車",
      "湾仔"
    ],
    "description": "湾仔のGloucester Road沿いにあるホンダの正規販売店。日本のホンダ車を香港で購入できる。",
    "detail": "Reliance Motorsが運営するホンダ香港の正規販売店。湾仔のMassMutual Tower G/FにあるショールームでHonda Civic・CR-V・HR-V等の最新モデルを展示。試乗・購入相談・ファイナンス（割賦）のサポートが可能。在住日本人にとってホンダは馴染みのあるブランドで、香港でも同様の日本品質のサービスが受けられる。",
    "menu": null,
    "source_url": "https://www.angloinfo.com/hong-kong/directory/hong-kong-car-dealers-sales-new-used-425",
    "source": "web_search",
    "status": "unverified",
    "ai_reviewed": true,
    "last_verified": "2026-04-05"
  },
  {
    "slug": "nissan-wan-chai-showroom",
    "name": "Nissan Wan Chai Showroom",
    "category": "car",
    "subcategory": "car-showroom",
    "area": "wan-chai",
    "address": "G/F, Jubilee Centre, 46 Gloucester Road, Wan Chai",
    "phone": null,
    "website": "https://en.nissan.com.hk",
    "hours": "月〜土 9:00〜19:00、日・祝 10:00〜19:00",
    "price_range": "車両価格による",
    "tags": [
      "日産",
      "新車",
      "試乗",
      "日本車",
      "湾仔"
    ],
    "description": "湾仔のGloucester Road沿いにある日産の正規販売店Honest Motors。日本車の新車購入が可能。",
    "detail": "Honest Motorsが運営する日産（Nissan）香港島の正規販売店。湾仔のJubilee Centre G/Fに位置し、Nissan Qashqai・Leaf（電気自動車）・Almera等の最新モデルを展示する。日産はゴーン氏の時代から香港でも人気の日本車ブランドの一つ。電気自動車Leafの試乗も可能。購入後のアフターサービスも含めた総合サポートを提供。",
    "menu": null,
    "source_url": "https://en.nissan.com.hk/dealer-finder.html",
    "source": "web_search",
    "status": "unverified",
    "ai_reviewed": true,
    "last_verified": "2026-04-05"
  }
]