[
  {
    "slug": "his-hong-kong",
    "name": "H.I.S. Hong Kong",
    "name_ja": "エイチ・アイ・エス 香港",
    "area": "Central",
    "address": "Central, Hong Kong",
    "phone": null,
    "website": "https://www.his-hk.com/",
    "description": "日本の大手旅行代理店の香港支店。セントラルに位置し、日本行き航空券・ホテル・パッケージツアーを日本語で手配可能。一時帰国の手配にも便利。",
    "tags": [
      "日本語対応",
      "日系旅行代理店",
      "航空券",
      "一時帰国"
    ],
    "hours": "要確認",
    "last_verified": "2026-03-27",
    "status": "unverified",
    "source": "website",
    "ai_reviewed": true,
    "phone_local": null,
    "email": null,
    "rating": null,
    "user_rating_count": null,
    "price_level": null,
    "photo_name": null
  },
  {
    "slug": "no1-travel-hk",
    "name": "No.1 Travel Hong Kong",
    "name_ja": "No.1トラベル 香港",
    "area": "Tsim Sha Tsui",
    "address": "Tsim Sha Tsui, Hong Kong",
    "phone": null,
    "website": "https://www.no1-travel.com/",
    "description": "香港在住日本人向け旅行代理店。チムサーチョイ（尖沙咀）に位置し、格安航空券・一時帰国パッケージ・東南アジア旅行等を日本語で手配。",
    "tags": [
      "日本語対応",
      "格安航空券",
      "一時帰国"
    ],
    "hours": "要確認",
    "last_verified": "2026-03-27",
    "status": "unverified",
    "source": "website",
    "ai_reviewed": true,
    "phone_local": null,
    "email": null,
    "rating": null,
    "user_rating_count": null,
    "price_level": null,
    "photo_name": null
  },
  {
    "slug": "walk-japan-limited",
    "name": "Walk Japan Limited",
    "name_ja": "ウォークジャパン",
    "area": "Hong Kong",
    "address": "24th Floor, Unit 59, Lee Garden 1, 33 Hysan Ave, Causeway Bay, Hong Kong",
    "lat": 22.2784,
    "lng": 114.1847,
    "phone": "+85237051214",
    "website": "http://www.walkjapan.com/",
    "description": "香港拠点の日本ウォーキングツアー専門会社。中山道・熊野古道など日本の歴史的街道を歩くガイド付きツアーを企画。英語ガイド。",
    "tags": [
      "日本旅行",
      "ウォーキングツアー",
      "香港拠点"
    ],
    "hours": null,
    "last_verified": "2026-03-28",
    "status": "unverified",
    "source": "google_maps",
    "place_id": "ChIJewMzOVcABDQRkIL2XQ1Js58",
    "priority": 0,
    "ai_reviewed": true,
    "phone_local": null,
    "email": null,
    "rating": null,
    "user_rating_count": null,
    "price_level": null,
    "photo_name": null
  },
  {
    "slug": "japan-visa-application-centre",
    "name": "Japan Visa Application Centre",
    "name_ja": "日本ビザ申請センター",
    "area": "North Point",
    "address": "7/F, B, 169號 Electric Rd, North Point, Hong Kong",
    "lat": 22.2875,
    "lng": 114.1916,
    "phone": "+85231677033",
    "website": "http://www.vfsglobal.com/japan/Hongkong/",
    "description": "VFS Global運営の日本ビザ申請センター。香港から日本への渡航ビザの申請手続きを受付。ビザ申請書類の提出・パスポート受取に対応。",
    "tags": [
      "ビザ申請",
      "日本渡航"
    ],
    "hours": "月〜金 8:30〜16:45",
    "last_verified": "2026-03-28",
    "status": "unverified",
    "source": "google_maps",
    "place_id": "ChIJq-IP2AEBBDQRGvsR44Hte74",
    "priority": 0,
    "ai_reviewed": true,
    "phone_local": null,
    "email": null,
    "rating": null,
    "user_rating_count": null,
    "price_level": null,
    "photo_name": null
  },
  {
    "slug": "egl-tours",
    "name": "EGL Tours 東瀛遊 銅鑼灣分行",
    "name_ja": "EGLツアーズ 銅鑼湾店",
    "area": "Hong Kong",
    "address": "Rm 608, 6/F, Hang Lung Centre, 2-20 Paterson St, Causeway Bay, Hong Kong",
    "lat": 22.2802,
    "lng": 114.186,
    "phone": "+85236920888",
    "website": "https://www.egltours.com/",
    "description": "香港大手旅行代理店。日本ツアーに強く、コーズウェイベイ店で日本行きパッケージツアー・航空券・ホテル手配を日本語対応で提供。",
    "tags": [
      "旅行代理店",
      "日本ツアー",
      "香港大手"
    ],
    "hours": "Monday: 10:30 AM – 7:30 PM / Tuesday: 10:30 AM – 7:30 PM / Wednesday: 10:30 AM – 7:30 PM / Thursday: 10:30 AM – 7:30 PM / Friday: 10:30 AM – 7:30 PM / Saturday: 10:30 AM – 7:30 PM / Sunday: 10:30 AM – 7:30 PM",
    "last_verified": "2026-03-28",
    "status": "unverified",
    "source": "google_maps",
    "place_id": "ChIJibrEcyIBBDQRryUxCBb_cfo",
    "priority": 0,
    "ai_reviewed": true,
    "phone_local": null,
    "email": null,
    "rating": null,
    "user_rating_count": null,
    "price_level": null,
    "photo_name": null
  },
  {
    "slug": "hk-japanese-tour-operators-association",
    "name": "HK Japanese Tour Operators Association",
    "name_ja": "香港日本人旅客手配業社協会",
    "area": "Hong Kong",
    "address": "11/F, Eu Yan Sang Tower, 11-15 Chatham Rd S, Tsim Sha Tsui, Hong Kong",
    "lat": 22.2969,
    "lng": 114.1751,
    "phone": "+85223122888",
    "website": "http://www.hjtoa.com/",
    "description": "香港の日本旅行専門業者で構成される業界団体。日本旅行を取り扱う加盟旅行代理店の情報提供を行い、信頼できる業者一覧を紹介する。",
    "tags": [
      "業界団体",
      "日本旅行"
    ],
    "hours": null,
    "last_verified": "2026-03-28",
    "status": "unverified",
    "source": "google_maps",
    "place_id": "ChIJp_MJ4PEABDQRVVkYF_LO0Is",
    "priority": 0,
    "ai_reviewed": true,
    "phone_local": null,
    "email": null,
    "rating": null,
    "user_rating_count": null,
    "price_level": null,
    "photo_name": null
  }
]
