[
  {
    "slug": "able-taiwan",
    "name": "ABLE Taiwan",
    "name_ja": "エイブル台湾店",
    "area": "Zhongshan",
    "address": "Room 1001, 10F, No. 96, Section 2, Zhongshan North Road, Zhongshan District, Taipei",
    "phone": "+886225110011",
    "website": "https://www.able-nw.com/taiwan/",
    "description": "日本の大手不動産チェーン・エイブルの台湾店。日本人スタッフが常駐し、物件探しから契約まで全て日本語で対応。駐在員・留学生・現地採用の日本人に対応。",
    "tags": [
      "日本語対応",
      "日本人スタッフ常駐",
      "賃貸"
    ],
    "hours": "台湾時間 9:00〜18:00（日曜・台湾祝日休）",
    "last_verified": "2026-03-26",
    "status": "unverified",
    "source": "website"
  },
  {
    "slug": "starts-taiwan",
    "name": "Starts Taiwan",
    "name_ja": "スターツ台湾",
    "area": "Zhongshan",
    "address": "Zhongshan District, Taipei",
    "phone": "+886225110508",
    "website": "https://kaigai.starts.co.jp/taiwan",
    "description": "日本のスターツグループの台湾拠点。40年以上の海外不動産サービスの実績を持ち、日本語で賃貸マンション・サービスアパートメント・オフィスの物件探しをサポート。",
    "tags": [
      "日本語対応",
      "賃貸",
      "オフィス"
    ],
    "hours": "台湾時間 9:00〜18:00",
    "last_verified": "2026-03-26",
    "status": "unverified",
    "source": "website"
  },
  {
    "slug": "papago-heya",
    "name": "PAPAGO Room Search Support",
    "name_ja": "PAPAGOお部屋探し支援室",
    "area": "Zhongshan",
    "address": "2F-3, No. 139, Songjiang Road, Zhongshan District, Taipei",
    "phone": "+886225111415",
    "website": "https://www.papago-taiwanheya.com/",
    "description": "台湾の不動産仲介資格を持つ日本人スタッフが対応する部屋探し支援サービス。留学生から駐在員まで幅広く対応。銀行口座開設・携帯契約などの生活立ち上げサポートも提供。",
    "tags": [
      "日本語対応",
      "日本人スタッフ",
      "賃貸",
      "生活サポート"
    ],
    "hours": "平日 10:00〜19:00（日本時間）",
    "last_verified": "2026-03-26",
    "status": "unverified",
    "source": "website"
  },
  {
    "slug": "shingi-fusaya-taipei",
    "name": "Sinyi Realty",
    "name_ja": "信義房屋",
    "area": "Zhongshan",
    "address": "Various locations in Taipei",
    "phone": null,
    "website": "https://www.sinyi.com.tw/",
    "description": "台湾最大の不動産仲介会社。日本にも子会社を持ち、日本語でのサポート体制がある。台北市内に多数の店舗を展開。",
    "tags": [
      "不動産",
      "台湾最大手",
      "日本語対応可"
    ],
    "hours": "平日 9:00〜18:00",
    "status": "unverified",
    "source": "website",
    "last_verified": "2026-03-27"
  },
  {
    "slug": "leopalace21-taipei",
    "name": "Leopalace21 Taipei",
    "name_ja": "レオパレス21 台北",
    "area": "Zhongshan",
    "address": "Zhongshan District, Taipei",
    "phone": null,
    "website": null,
    "description": "日本の賃貸マンションチェーン。家具付き物件を中心に、日本人駐在員向けの短期〜長期賃貸を提供。日本語対応。",
    "tags": [
      "賃貸",
      "日系",
      "家具付き",
      "日本語対応"
    ],
    "hours": "平日 9:00〜18:00",
    "status": "unverified",
    "source": "google_maps",
    "last_verified": "2026-03-27"
  }
]