[
  {
    "slug": "his-tours-phrom-phong",
    "name": "HIS Tours Phrom Phong",
    "name_ja": "HIS ツアーズ プロム ポン",
    "area": "Bangkok",
    "address": "595/22 Ellsie Boutique Mall ชั้น 1 ห้องหมายเลข A4, B10, B11, ซ. สุขุมวิท 33/1 แขวงคลองตันเหนือ เขตวัฒนา กรุงเทพมหานคร 10110, Thailand",
    "lat": 13.7321,
    "lng": 100.5684,
    "phone": "+6620220908",
    "website": "https://his-bkk.com/",
    "description": "日本の大手旅行会社HISのバンコク支店。タイ国内旅行・海外旅行・航空券・ホテル・現地ツアーを手配。バンコク・シラチャ・チェンマイの3拠点で日本語スタッフが対応。法人の出張手配にも対応。",
    "tags": [
      "旅行",
      "ツアー",
      "日本語対応"
    ],
    "hours": "Monday: 9:30 AM – 1:00 PM, 2:00 – 5:30 PM / Tuesday: 9:30 AM – 1:00 PM, 2:00 – 5:30 PM / Wednesday: 9:30 AM – 1:00 PM, 2:00 – 5:30 PM / Thursday: 9:30 AM – 1:00 PM, 2:00 – 5:30 PM / Friday: 9:30 AM – 1:00 PM, 2:00 – 5:30 PM / Saturday: 9:30 AM – 1:00 PM, 2:00 – 5:30 PM / Sunday: 9:30 AM – 1:00 PM, 2:00 – 5:30 PM",
    "last_verified": "2026-03-28",
    "status": "unverified",
    "source": "google_maps",
    "place_id": "ChIJldVNUKqf4jARgEpVmpnbrbc",
    "priority": 0,
    "ai_reviewed": true
  },
  {
    "slug": "jtb-thailand",
    "name": "JTB (Thailand) Limited",
    "name_ja": "JTBタイランド",
    "area": "Silom",
    "address": "54 Harindhorn Building, 9th Floor, Rooms 9C, 9D, 9E, North Sathorn Road, Silom, Bangrak, Bangkok 10500",
    "phone": "+6622300499",
    "website": "https://th.jtbtrip.com/pages/about-jtb",
    "description": "日本の大手旅行会社JTBのタイ法人。日本行きツアー・航空券・ホテル・ビザ手配を日本語で提供。法人の出張手配にも対応。",
    "tags": [
      "日本語対応",
      "旅行代理店",
      "航空券",
      "法人対応"
    ],
    "hours": "月-金 9:00-18:00（土日祝休み）",
    "last_verified": "2026-03-26",
    "status": "unverified",
    "source": "website",
    "ai_reviewed": true
  },
  {
    "slug": "wendy-tour-bangkok",
    "name": "Wendy Tour Bangkok",
    "name_ja": "ウェンディツアー バンコク",
    "area": "Sukhumvit",
    "address": "Sukhumvit, Bangkok",
    "phone": null,
    "website": null,
    "description": "タイ国内ツアー・空港送迎・ゴルフ手配などを日本語で提供する老舗旅行会社。スクンビット通り沿いに事務所を構え、在住日本人・観光客に対応",
    "tags": [
      "日本語対応",
      "ツアー",
      "空港送迎"
    ],
    "hours": "月〜土 9:00-18:00",
    "status": "unverified",
    "source": "google_maps",
    "last_verified": "2026-03-27",
    "ai_reviewed": true
  },
  {
    "slug": "tripull-bangkok",
    "name": "TRIPULL Co., Ltd.",
    "name_ja": "トリプル",
    "area": "Silom",
    "address": "68-68/6 S&B Tower, 1st Floor, Room 116, Pan Rd., Silom, Bangrak, Bangkok 10500",
    "phone": "+6628644227",
    "website": "https://tripull.asia/",
    "description": "バンコク拠点の現地オプショナルツアー会社。日本語ガイド手配・プライベートツアー・チャータータクシー・ディナークルーズの予約に対応。バンコク発の日帰りツアーが充実。",
    "tags": [
      "日本語対応",
      "現地ツアー",
      "日本語ガイド",
      "チャーター"
    ],
    "hours": null,
    "status": "unverified",
    "source": "website",
    "last_verified": "2026-03-27",
    "ai_reviewed": true
  },
  {
    "slug": "golf-tabirand-bangkok",
    "name": "Golf Tabirand",
    "name_ja": "Golf旅ランド",
    "area": "Bangkok",
    "address": "Bangkok, Thailand",
    "phone": null,
    "website": "https://www.golfthabiland.com/",
    "description": "タイ全土のゴルフ場予約・送迎サービスを提供。バンコク・パタヤ周辺の名門コースからプライベートコースまで幅広く取り扱い。空港からの直行ゴルフプランもあり。日本語で予約可能。",
    "tags": [
      "日本語対応",
      "ゴルフ予約",
      "送迎付き"
    ],
    "hours": null,
    "status": "unverified",
    "source": "website",
    "last_verified": "2026-03-27",
    "ai_reviewed": true
  },
  {
    "slug": "golfasian-bangkok",
    "name": "Golfasian Co., Ltd.",
    "name_ja": "ゴルフアジアン",
    "area": "Bangkok",
    "address": "Bangkok, Thailand",
    "phone": "+66847043344",
    "website": "https://www.golfasian.com/",
    "description": "アジアを代表するゴルフツアーオペレーター。タイ・ベトナム・カンボジア・マレーシア・インドネシア・フィリピンのゴルフパッケージを手配。バンコク発の日帰りゴルフツアーが充実。英語対応。",
    "tags": [
      "ゴルフ",
      "ツアー",
      "送迎付き"
    ],
    "hours": null,
    "status": "unverified",
    "source": "website",
    "last_verified": "2026-03-27",
    "ai_reviewed": true
  },
  {
    "slug": "new-toyo-travel-bangkok",
    "name": "New Toyo Travel Co., Ltd.",
    "name_ja": "ニュー トヨ トラベル Co., Ltd.",
    "area": "Bangkok",
    "address": "Bangkok, Thailand",
    "phone": null,
    "website": "https://www.newtoyotravel.com/",
    "description": "バンコク拠点の旅行代理店。日本行きのパッケージツアー・航空券手配・ホテル予約に対応。タイ国内旅行から海外旅行まで幅広く取り扱い。日本語対応可能。",
    "tags": [
      "日本語対応",
      "旅行代理店",
      "航空券",
      "パッケージツアー"
    ],
    "hours": null,
    "status": "unverified",
    "source": "website",
    "last_verified": "2026-03-27",
    "ai_reviewed": true
  },
  {
    "slug": "pandabus-bangkok",
    "name": "Panda Bus Bangkok",
    "name_ja": "パンダバス バンコク",
    "area": "Bangkok",
    "address": "Bangkok, Thailand",
    "phone": null,
    "website": "https://www.pandabus.com/bangkok/",
    "description": "日本語ガイド付きオプショナルツアーを提供するバンコクの旅行会社。アユタヤ日帰りツアー、水上マーケット、バンコク市内観光など多彩なツアーラインナップ。日本語サイトからオンライン予約可能。",
    "tags": [
      "日本語対応",
      "オプショナルツアー",
      "日本語ガイド",
      "オンライン予約"
    ],
    "hours": null,
    "status": "unverified",
    "source": "website",
    "last_verified": "2026-03-27",
    "ai_reviewed": true
  },
  {
    "slug": "haruka-japanese-reservation-bangkok",
    "name": "HARUKA Japanese Reservation Center",
    "name_ja": "ハルカ 日本 リザベーション センター",
    "area": "Ratchathewi",
    "address": "1091/112 Soi 33, New Phetchaburi Rd., Makkasan, Rajthevee, Bangkok 10400",
    "phone": "+6621850237",
    "website": "https://www.nihongoyoyaku.com/",
    "description": "バンコクの日本語予約サービス。空港リムジン送迎・スパ・ゴルフ場予約・ディナークルーズ・オプショナルツアーを日本語で予約可能。日本からの電話予約にも対応（070-8425-0723）。",
    "tags": [
      "日本語対応",
      "予約代行",
      "空港送迎",
      "ゴルフ予約"
    ],
    "hours": "平日 9:00-17:30 / 土日 9:00-15:00",
    "status": "unverified",
    "source": "website",
    "last_verified": "2026-03-27",
    "ai_reviewed": true
  },
  {
    "slug": "enjoy-happy-tour-bangkok",
    "name": "Enjoy Happy Tour (Bangkok Golf)",
    "name_ja": "エンジョイハッピーツアー（バンコクゴルフ）",
    "area": "Bangkok",
    "address": "Bangkok, Thailand",
    "phone": null,
    "website": "https://chiangmaihappytour.com/enjoy/golf-bangkok/",
    "description": "バンコク周辺のゴルフ場予約・送迎サービスを提供。日本語ガイド付きゴルフツアーを手配。バンコク・パタヤ・ホアヒンの名門コースから初心者向けコースまで幅広く対応。",
    "tags": [
      "日本語対応",
      "ゴルフ予約",
      "送迎付き",
      "日本語ガイド"
    ],
    "hours": null,
    "status": "unverified",
    "source": "website",
    "last_verified": "2026-03-27",
    "ai_reviewed": true
  },
  {
    "slug": "veltra-bangkok-tours",
    "name": "VELTRA Bangkok",
    "name_ja": "ベルトラ バンコク",
    "area": "Bangkok",
    "address": "Bangkok, Thailand",
    "phone": null,
    "website": "https://www.veltra.com/jp/asia/thailand/bangkok/",
    "description": "日本最大級のオプショナルツアー予約サイト「VELTRA」のバンコクページ。アユタヤ遺跡ツアー・水上マーケット・ゴルフ・スパ・ディナークルーズなど多彩なツアーを日本語で予約可能。",
    "tags": [
      "日本語対応",
      "オプショナルツアー",
      "オンライン予約"
    ],
    "hours": null,
    "status": "unverified",
    "source": "website",
    "last_verified": "2026-03-27",
    "ai_reviewed": true
  },
  {
    "slug": "japan-all-pass-co-ltd",
    "name": "JAPAN ALL PASS CO.,LTD.",
    "name_ja": "ジャパン オール パッス Co.,Ltd.",
    "area": "Bangkok",
    "address": "625 อาคารทัศนียา ชั้น 5 ยูนิต C ซอยรามคำแหง 39 ถนนประชาอุทิศ, วังทองหลาง, Bangkok 10310, Thailand",
    "lat": 13.7671,
    "lng": 100.5947,
    "phone": "+6625147473",
    "website": "https://japanallpass.nooxs.com/",
    "description": "タイ人向け日本旅行ツアーを専門に手がける旅行会社。日本各地のツアーパッケージを企画・販売、バンコクに事務所を構える",
    "tags": [
      "旅行",
      "ツアー",
      "日本語対応"
    ],
    "hours": "Monday: 8:30 AM – 5:30 PM / Tuesday: 8:30 AM – 5:30 PM / Wednesday: 8:30 AM – 5:30 PM / Thursday: 8:30 AM – 5:30 PM / Friday: 8:30 AM – 5:30 PM / Saturday: 8:30 AM – 5:30 PM / Sunday: Closed",
    "last_verified": "2026-03-28",
    "status": "unverified",
    "source": "google_maps",
    "place_id": "ChIJ45LMjnKe4jARoouQRXcFxGI",
    "priority": 0,
    "ai_reviewed": true
  },
  {
    "slug": "by-compax-world-co-ltd",
    "name": "ทัวร์ญี่ปุ่น ทัวร์ญี่ปุ่นคุณภาพ ทัวร์ญี่ปุ่นพรีเมี่ยม By Compax World Co.,Ltd.",
    "name_ja": "ทวรญปน ทวรญปนคณภาพ ทวรญปนพรเมยม By Compax ワールド Co.,Ltd.",
    "area": "Bangkok",
    "address": "559/201 ธนาพัฒน์เฮ้าส์ ซ.นนทรี 20 ถ.นนทรี แขวงช่องนนทรี​ เขตยานนาวา Khwaeng Chong Nonsi, Khet Yan Nawa, Krung Thep Maha Nakhon 10120, Thailand",
    "lat": 13.6889,
    "lng": 100.5424,
    "phone": "+6621691766",
    "website": "https://www.compaxworld.com/",
    "description": "プレミアム日本旅行ツアーを専門に企画・催行するタイの旅行会社。高品質な日本ツアーパッケージを提供、バンコクに所在",
    "tags": [
      "旅行",
      "ツアー",
      "日本語対応"
    ],
    "hours": "Monday: 9:00 AM – 12:00 PM, 1:00 – 5:00 PM / Tuesday: 9:00 AM – 12:00 PM, 1:00 – 5:00 PM / Wednesday: 9:00 AM – 12:00 PM, 1:00 – 5:00 PM / Thursday: 9:00 AM – 12:00 PM, 1:00 – 5:00 PM / Friday: 9:00 AM – 12:00 PM, 1:00 – 5:00 PM / Saturday: Closed / Sunday: Closed",
    "last_verified": "2026-03-28",
    "status": "unverified",
    "source": "google_maps",
    "place_id": "ChIJBYrJclif4jARP3PfDvrDKuo",
    "priority": 0,
    "ai_reviewed": true
  },
  {
    "slug": "akgo-tour",
    "name": "AKGo Tour",
    "name_ja": "AKGo ツアー",
    "area": "Bangkok",
    "address": "999/9 Rama I Rd, Khwaeng Pathum Wan, Pathum Wan, Krung Thep Maha Nakhon 10330, Thailand",
    "lat": 13.7465,
    "lng": 100.5381,
    "phone": "+66971176137",
    "website": "http://www.akgotour.com/",
    "description": "日本旅行ツアーを中心に手がけるバンコクの旅行代理店。日本各地のツアーを企画・催行、グループ・個人旅行に対応",
    "tags": [
      "旅行",
      "ツアー",
      "日本語対応"
    ],
    "hours": "Monday: 8:00 AM – 5:00 PM / Tuesday: 8:00 AM – 5:00 PM / Wednesday: 8:00 AM – 5:00 PM / Thursday: 8:00 AM – 5:00 PM / Friday: 8:00 AM – 5:00 PM / Saturday: 8:00 AM – 5:00 PM / Sunday: 8:00 AM – 5:00 PM",
    "last_verified": "2026-03-28",
    "status": "unverified",
    "source": "google_maps",
    "place_id": "ChIJQz80demf4jARbEJeyLCVp7c",
    "priority": 0,
    "ai_reviewed": true
  },
  {
    "slug": "panda-travel-agency",
    "name": "パンダバス (Panda Travel Agency) バンコク",
    "name_ja": "パンダバス バンコク",
    "area": "Bangkok",
    "address": "33 วอลล์สตรีท ทาวเวอร์ 58 Surawong Rd, Khwaeng Suriya Wong, Khet Bang Rak, Krung Thep Maha Nakhon 10500, Thailand",
    "lat": 13.7296,
    "lng": 100.5325,
    "phone": "+6626329914",
    "website": "http://www.pandabus.com/thailand",
    "description": "タイ国内の日帰りツアー・空港送迎・ゴルフ手配を日本語で提供する旅行会社。バンコクを拠点にタイ各地のオプショナルツアーを催行。",
    "tags": [
      "旅行",
      "ツアー",
      "日本語対応"
    ],
    "hours": "Monday: 9:00 AM – 6:00 PM / Tuesday: 9:00 AM – 6:00 PM / Wednesday: 9:00 AM – 6:00 PM / Thursday: 9:00 AM – 6:00 PM / Friday: 9:00 AM – 6:00 PM / Saturday: 9:00 AM – 6:00 PM / Sunday: 9:00 AM – 6:00 PM",
    "last_verified": "2026-03-28",
    "status": "unverified",
    "source": "google_maps",
    "place_id": "ChIJFWvZxK2f4jARx8Qs-PTMAQk",
    "priority": 0,
    "ai_reviewed": true
  },
  {
    "slug": "pp",
    "name": "旅行会社 PPツアーズ",
    "name_ja": "旅行会社 PPツアーズ",
    "area": "Bangkok",
    "address": "Silom64 Building 4th Floor 64, ถ.สีลม Suriyawongse, เขตบางรัก กรุงเทพมหานคร 10500, Thailand",
    "lat": 13.7285,
    "lng": 100.5334,
    "phone": "+6626525350",
    "website": "https://www.pptours-bkk.com/",
    "description": "BTSサラデーン駅直結のSilom64ビル4階にある旅行会社。タニヤ通りから徒歩1分。ホテル・サービスアパートの予約、ツアー・クーポン、ゴルフ手配、レンタカー、レンタル携帯電話を提供。日本人スタッフが常駐。",
    "tags": [
      "旅行",
      "ツアー",
      "日本語対応"
    ],
    "hours": "Monday: 9:00 AM – 7:00 PM / Tuesday: 9:00 AM – 7:00 PM / Wednesday: 9:00 AM – 7:00 PM / Thursday: 9:00 AM – 7:00 PM / Friday: 9:00 AM – 7:00 PM / Saturday: 9:00 AM – 6:00 PM / Sunday: 9:00 AM – 6:00 PM",
    "last_verified": "2026-03-28",
    "status": "unverified",
    "source": "google_maps",
    "place_id": "ChIJMYS4732Z4jARANNDjVC3sa0",
    "priority": 0,
    "ai_reviewed": true
  },
  {
    "slug": "backyard-travel",
    "name": "Backyard Travel",
    "name_ja": "バックヤード トラベル",
    "area": "Bangkok",
    "address": "Level 18, Park Ventures Ecoplex, 57 ถ. วิทยุ แขวงลุมพินี เขตปทุมวัน กรุงเทพมหานคร 10330, Thailand",
    "lat": 13.7426,
    "lng": 100.548,
    "phone": "+6626339074",
    "website": "http://www.backyardtravel.com/",
    "description": "東南アジア各国のカスタムツアーを手がけるバンコクの旅行会社。個人旅行やオーダーメイドツアーに対応、英語・日本語サポートあり",
    "tags": [
      "旅行",
      "ツアー",
      "日本語対応"
    ],
    "hours": "Monday: 9:00 AM – 6:00 PM / Tuesday: 9:00 AM – 6:00 PM / Wednesday: 9:00 AM – 6:00 PM / Thursday: 9:00 AM – 6:00 PM / Friday: 9:00 AM – 6:00 PM / Saturday: Closed / Sunday: Closed",
    "last_verified": "2026-03-28",
    "status": "unverified",
    "source": "google_maps",
    "place_id": "ChIJXx5Wjdye4jARRP0IbfnfrsI",
    "priority": 0,
    "ai_reviewed": true
  },
  {
    "slug": "big-elephant-tour-co-ltd",
    "name": "Big Elephant Tour Co.,Ltd.",
    "name_ja": "ビッグ エレファント ツアー Co.,Ltd.",
    "area": "Bangkok",
    "address": "282 Trok Taladnoi Soi Duangtawan, Charoenkrung Road, Taladnoi, Khet Samphanthawong, Bangkok, 10100, แขวงตลาดน้อย เขตสัมพันธวงศ์ กรุงเทพมหานคร 10100, Thailand",
    "lat": 13.7326,
    "lng": 100.5146,
    "phone": "+6626396262",
    "website": null,
    "description": "タイ国内ツアー・日本旅行を手がけるバンコクの旅行会社。象乗りツアーなどタイならではの体験ツアーも企画・催行",
    "tags": [
      "旅行",
      "ツアー",
      "日本語対応"
    ],
    "hours": null,
    "last_verified": "2026-03-28",
    "status": "unverified",
    "source": "google_maps",
    "place_id": "ChIJCQZE4tiY4jARWPEgUTcFKXw",
    "priority": 0,
    "ai_reviewed": true
  },
  {
    "slug": "japan-holiday-tour-and-travel",
    "name": "Japan Holiday Tour And Travel",
    "name_ja": "ジャパン ホリデー ツアー & トラベル",
    "area": "Bangkok",
    "address": "Jl. Brastagi No.16 C, Sidodadi, Kec. Medan Tim., Kota Medan, Sumatera Utara 20233, Indonesia",
    "lat": 3.5971,
    "lng": 98.6927,
    "phone": "+6282166249990",
    "website": "http://instagram.com/japanholiday",
    "description": "日本旅行に特化したバンコクの旅行代理店。日本のホリデーツアーパッケージを企画・販売、タイ在住者の日本渡航をサポート",
    "tags": [
      "旅行",
      "ツアー",
      "日本語対応"
    ],
    "hours": "Monday: 9:00 AM – 5:00 PM / Tuesday: 9:00 AM – 5:00 PM / Wednesday: 9:00 AM – 5:00 PM / Thursday: 9:00 AM – 5:00 PM / Friday: 9:00 AM – 5:00 PM / Saturday: 9:00 AM – 3:00 PM / Sunday: Closed",
    "last_verified": "2026-03-28",
    "status": "unverified",
    "source": "google_maps",
    "place_id": "ChIJ95Mqm7UxMTARalMS1lQEwLU",
    "priority": 0,
    "ai_reviewed": true
  },
  {
    "slug": "thailand-holiday-group-travel-agency",
    "name": "Thailand Holiday Group - Travel Agency",
    "name_ja": "タイランド ホリデー グループ - トラベル エージェンシー",
    "area": "Bangkok",
    "address": "252, 8-10 Soi Attakawee 2, Klongton, Klongtoey, Krung Thep Maha Nakhon 10110, Thailand",
    "lat": 13.7214,
    "lng": 100.5668,
    "phone": "+6622586686",
    "website": "http://www.thailandholidaygroup.com/",
    "description": "タイ国内・海外旅行を手がけるバンコクの総合旅行代理店。グループツアーや団体旅行の手配を得意とし、日本行きツアーも取り扱い",
    "tags": [
      "旅行",
      "ツアー",
      "日本語対応"
    ],
    "hours": null,
    "last_verified": "2026-03-28",
    "status": "unverified",
    "source": "google_maps",
    "place_id": "ChIJLV6OEfef4jARIAbueAbDxKs",
    "priority": 0,
    "ai_reviewed": false
  },
  {
    "slug": "club-thailand",
    "name": "Club Thailand",
    "name_ja": "クラブ タイランド",
    "area": "Bangkok",
    "address": "15 Soi Sukhumvit 35, Khwaeng Khlong Tan Nuea, Watthana, Krung Thep Maha Nakhon 10110, Thailand",
    "lat": 13.7333,
    "lng": 100.5687,
    "phone": "+6626621191",
    "website": "https://www.thailandcard.com/",
    "description": "タイのトラベルカード・観光情報を提供するバンコクの旅行関連サービス。タイ国内の観光スポットやアクティビティの予約に対応",
    "tags": [
      "旅行",
      "ツアー",
      "日本語対応"
    ],
    "hours": "Monday: 10:00 AM – 7:00 PM / Tuesday: 10:00 AM – 7:00 PM / Wednesday: 10:00 AM – 7:00 PM / Thursday: 10:00 AM – 7:00 PM / Friday: 10:00 AM – 7:00 PM / Saturday: 9:00 AM – 6:00 PM / Sunday: 9:00 AM – 6:00 PM",
    "last_verified": "2026-03-28",
    "status": "unverified",
    "source": "google_maps",
    "place_id": "ChIJf7YrAQKf4jARlug66JzjW84",
    "priority": 0,
    "ai_reviewed": false
  },
  {
    "slug": "travel-sensei",
    "name": "Travel Sensei",
    "name_ja": "トラベル 先生",
    "area": "Bangkok",
    "address": "291, 138 Blocs 77 On Nut Rd, Khwaeng Phra Khanong Nuea, Watthana, Krung Thep Maha Nakhon 10110, Thailand",
    "lat": 13.7104,
    "lng": 100.6018,
    "phone": null,
    "website": "https://travelsensei.co/",
    "description": "日本語ガイド付きツアーを手がけるバンコクの旅行会社。「先生」の名の通り現地の深い知識を持つガイドによるカスタムツアーを提供",
    "tags": [
      "旅行",
      "ツアー",
      "日本語対応"
    ],
    "hours": "Monday: Open 24 hours / Tuesday: Open 24 hours / Wednesday: Open 24 hours / Thursday: Open 24 hours / Friday: Open 24 hours / Saturday: Open 24 hours / Sunday: Open 24 hours",
    "last_verified": "2026-03-28",
    "status": "unverified",
    "source": "google_maps",
    "place_id": "ChIJBxtsOQ2f4jAR-E2BJf7kFW4",
    "priority": 0,
    "ai_reviewed": true
  },
  {
    "slug": "sky-access-travel-co-ltd",
    "name": "Sky Access Travel Co.,Ltd.",
    "name_ja": "スカイ Access トラベル Co.,Ltd.",
    "area": "Bangkok",
    "address": "11th Floor, Room J, Sitthivorakit Building, 5 Soi Pipat, แขวงสีลม เขตบางรัก กรุงเทพมหานคร 10500, Thailand",
    "lat": 13.727,
    "lng": 100.5311,
    "phone": "+6622351581",
    "website": "https://skyaccesstravel.com/",
    "description": "航空券手配・ツアー企画を手がけるバンコクの旅行会社。日本行き航空券の手配やパッケージツアーの販売に対応",
    "tags": [
      "旅行",
      "ツアー",
      "日本語対応"
    ],
    "hours": "Monday: 9:00 AM – 6:00 PM / Tuesday: 9:00 AM – 6:00 PM / Wednesday: 9:00 AM – 6:00 PM / Thursday: 9:00 AM – 6:00 PM / Friday: 9:00 AM – 6:00 PM / Saturday: 9:00 AM – 1:00 PM / Sunday: Closed",
    "last_verified": "2026-03-28",
    "status": "unverified",
    "source": "google_maps",
    "place_id": "ChIJwzFRbSaf4jARGNBZ5ad_l9s",
    "priority": 0,
    "ai_reviewed": true
  },
  {
    "slug": "hi-japan",
    "name": "Hi Japan",
    "name_ja": "ヒ ジャパン",
    "area": "Bangkok",
    "address": "Thanon Sukhonthasawat, Khwaeng Lat Phrao, Khet Lat Phrao, Krung Thep Maha Nakhon 10230, Thailand",
    "lat": 13.8229,
    "lng": 100.609,
    "phone": "+66967422942",
    "website": "https://www.hijapantour.com/",
    "description": "タイ人向け日本旅行ツアーを専門に手がける旅行会社。日本各地のツアーパッケージを豊富に取り揃え、バンコクに事務所を構える",
    "tags": [
      "旅行",
      "ツアー",
      "日本語対応"
    ],
    "hours": "Monday: 9:00 AM – 6:00 PM / Tuesday: 9:00 AM – 6:00 PM / Wednesday: 9:00 AM – 6:00 PM / Thursday: 9:00 AM – 6:00 PM / Friday: 9:00 AM – 6:00 PM / Saturday: Closed / Sunday: Closed",
    "last_verified": "2026-03-28",
    "status": "unverified",
    "source": "google_maps",
    "place_id": "ChIJOX3a0INiHTERY3rnJ6fJHPU",
    "priority": 0,
    "ai_reviewed": true
  },
  {
    "slug": "japan-guide-company-limited",
    "name": "Japan Guide Company Limited",
    "name_ja": "ジャパン ガイド カンパニー リミテド",
    "area": "Bangkok",
    "address": "300 Soi On Nut 10, Khwaeng Suan Luang, Khet Suan Luang, Krung Thep Maha Nakhon 10250, Thailand",
    "lat": 13.7074,
    "lng": 100.6081,
    "phone": "+6623312856",
    "website": null,
    "description": "日本旅行の専門ガイドサービスを提供するバンコクの旅行会社。日本語対応の現地ガイド手配やカスタムツアーの企画に対応",
    "tags": [
      "旅行",
      "ツアー",
      "日本語対応"
    ],
    "hours": "Monday: 9:00 AM – 6:00 PM / Tuesday: 9:00 AM – 6:00 PM / Wednesday: 9:00 AM – 6:00 PM / Thursday: 9:00 AM – 6:00 PM / Friday: 9:00 AM – 6:00 PM / Saturday: Closed / Sunday: Closed",
    "last_verified": "2026-03-28",
    "status": "unverified",
    "source": "google_maps",
    "place_id": "ChIJPXP9C-if4jARLsTsK3p2Wd0",
    "priority": 0,
    "ai_reviewed": true
  },
  {
    "slug": "my-chiang-mai-tour",
    "name": "My Chiang Mai Tour",
    "name_ja": "マイ チェン マイ ツアー",
    "area": "Chiang Mai",
    "address": "92 11 Sridonchai Rd, Tambon Chang Khlan, Amphoe Mueang Chiang Mai, Chang Wat Chiang Mai 50100, Thailand",
    "lat": 18.781,
    "lng": 99.0028,
    "phone": "+66884343199",
    "website": "http://mychiangmaitour.com/",
    "description": "チェンマイ発の現地ツアーを企画・催行する旅行会社。寺院巡り・山岳民族村訪問・象保護施設など北部タイの体験ツアーを提供",
    "tags": [
      "旅行",
      "ツアー",
      "日本語対応"
    ],
    "hours": "Monday: 9:00 AM – 5:30 PM / Tuesday: 9:00 AM – 5:30 PM / Wednesday: 9:00 AM – 5:30 PM / Thursday: 9:00 AM – 5:30 PM / Friday: 9:00 AM – 5:30 PM / Saturday: 9:00 AM – 5:30 PM / Sunday: 9:00 AM – 5:30 PM",
    "last_verified": "2026-03-28",
    "status": "unverified",
    "source": "google_maps",
    "place_id": "ChIJic7K2bgi2jARTqkNPxF1uQA",
    "priority": 0,
    "ai_reviewed": true
  },
  {
    "slug": "nimo-kanko-co-ltd",
    "name": "NIMO KANKO CO.,LTD.",
    "name_ja": "ニモ カンコ Co.,Ltd.",
    "area": "Chiang Mai",
    "address": "206/4 หมู่2 Tambon Don Kaeo, Amphoe Mae Rim, Chang Wat Chiang Mai 50180, Thailand",
    "lat": 18.8691,
    "lng": 98.9642,
    "phone": null,
    "website": "https://www.facebook.com/Nimokankou?mibextid=LQQJ4d",
    "description": "チェンマイを拠点とする日系観光会社。北部タイの観光ツアー・ゴルフ手配・空港送迎などを日本語で対応、Facebookで情報発信",
    "tags": [
      "旅行",
      "ツアー",
      "日本語対応"
    ],
    "hours": "Monday: 8:30 AM – 9:00 PM / Tuesday: 8:30 AM – 9:00 PM / Wednesday: 8:30 AM – 9:00 PM / Thursday: 8:30 AM – 9:00 PM / Friday: 8:30 AM – 9:00 PM / Saturday: 9:00 AM – 6:00 PM / Sunday: 9:00 AM – 3:00 PM",
    "last_verified": "2026-03-28",
    "status": "unverified",
    "source": "google_maps",
    "place_id": "ChIJN6KOpQc72jARwolQFyKNJCA",
    "priority": 0,
    "ai_reviewed": true
  },
  {
    "slug": "star-visa-service-chang-moi",
    "name": "Star Visa Service - Chang Moi",
    "name_ja": "スター ビザ サービス - チャング モイ",
    "area": "Chiang Mai",
    "address": "419, 3 Wichayanon Rd, Tambon Chang Moi, Amphoe Mueang Chiang Mai, Chang Wat Chiang Mai 50300, Thailand",
    "lat": 18.7946,
    "lng": 98.9967,
    "phone": "+66956464792",
    "website": "https://www.starvisaservice.com/",
    "description": "チェンマイ・チャンモイ地区にあるビザ手続き代行サービス。タイのビザ延長・更新手続きをサポート、旅行関連の相談にも対応",
    "tags": [
      "旅行",
      "ツアー",
      "日本語対応"
    ],
    "hours": "Monday: 8:00 AM – 6:00 PM / Tuesday: 8:00 AM – 6:00 PM / Wednesday: 8:00 AM – 6:00 PM / Thursday: 8:00 AM – 6:00 PM / Friday: 8:00 AM – 6:00 PM / Saturday: 8:00 AM – 6:00 PM / Sunday: Closed",
    "last_verified": "2026-03-28",
    "status": "unverified",
    "source": "google_maps",
    "place_id": "ChIJZ6zk2ro62jARWhh46EnCou8",
    "priority": 0,
    "ai_reviewed": true
  },
  {
    "slug": "japan-specialist-travel",
    "name": "Japan Specialist Travel",
    "name_ja": "ジャパン スペシャリスト トラベル",
    "area": "Chiang Mai",
    "address": "Level 3/360 Kent St, Sydney NSW 2000, Australia",
    "lat": -33.8702,
    "lng": 151.2049,
    "phone": "+61280988660",
    "website": "https://www.tourjapan.com.au/",
    "description": "日本旅行に特化したチェンマイの旅行会社。日本各地の観光ツアーを企画・販売、タイ北部在住者の日本渡航をサポート",
    "tags": [
      "旅行",
      "ツアー",
      "日本語対応"
    ],
    "hours": null,
    "last_verified": "2026-03-28",
    "status": "unverified",
    "source": "google_maps",
    "place_id": "ChIJRzT1kD6uEmsRt3KYCqukMlY",
    "priority": 0,
    "ai_reviewed": true
  },
  {
    "slug": "japa-tour-company",
    "name": "Japa Tour Company",
    "name_ja": "ジャパ ツアー カンパニー",
    "area": "Chiang Mai",
    "address": "608 2, Tambon Mae Yao, Amphoe Mueang Chiang Rai, Chang Wat Chiang Rai 57100, Thailand",
    "lat": 19.9452,
    "lng": 99.8063,
    "phone": "+66871838336",
    "website": "https://www.japatour.com/",
    "description": "日本ツアーを専門に手がけるチェンマイの旅行代理店。日本各地のパッケージツアーを企画・催行、グループ・個人旅行に対応",
    "tags": [
      "旅行",
      "ツアー",
      "日本語対応"
    ],
    "hours": null,
    "last_verified": "2026-03-28",
    "status": "unverified",
    "source": "google_maps",
    "place_id": "ChIJzSEJxWcG1zARg-t679XRMmA",
    "priority": 0,
    "ai_reviewed": true
  },
  {
    "slug": "chiang-mai-golf-tours",
    "name": "Chiang Mai Golf Tours",
    "name_ja": "チェン マイ ゴルフ ツアーズ",
    "area": "Chiang Mai",
    "address": "Thanon Chiang Mai-Lamphun, A. Muang, Amphoe Mueang Chiang Mai, Chang Wat Chiang Mai 50000, Thailand",
    "lat": 18.7656,
    "lng": 99.0055,
    "phone": "+66897550363",
    "website": "http://www.chiangmaigolftours.com/",
    "description": "チェンマイ周辺のゴルフツアーを専門に手がける旅行会社。北部タイのゴルフコース予約・送迎・宿泊手配をワンストップで提供",
    "tags": [
      "旅行",
      "ツアー",
      "日本語対応"
    ],
    "hours": "Monday: Open 24 hours / Tuesday: Open 24 hours / Wednesday: Open 24 hours / Thursday: Open 24 hours / Friday: Open 24 hours / Saturday: Open 24 hours / Sunday: Open 24 hours",
    "last_verified": "2026-03-28",
    "status": "unverified",
    "source": "google_maps",
    "place_id": "ChIJR9BOqhsw2jARi4xGbkW4doQ",
    "priority": 0,
    "ai_reviewed": true
  },
  {
    "slug": "r-s-n-tour-ltd-part",
    "name": "R.S.N. TOUR LTD., PART.",
    "name_ja": "R.S.N. ツアー LTD., PART.",
    "area": "Chiang Mai",
    "address": "299/27 Tambon Tha Sala, Amphoe Mueang Chiang Mai, Chang Wat Chiang Mai 50000, Thailand",
    "lat": 18.7784,
    "lng": 99.0301,
    "phone": "+6653262050",
    "website": "http://www.rsn-chiangmai-travel.com/",
    "description": "チェンマイを拠点とする旅行会社。北部タイの観光ツアー・トレッキング・文化体験ツアーなどを企画・催行、空港送迎にも対応",
    "tags": [
      "旅行",
      "ツアー",
      "日本語対応"
    ],
    "hours": "Monday: 9:00 AM – 4:00 PM / Tuesday: 9:00 AM – 4:00 PM / Wednesday: 9:00 AM – 4:00 PM / Thursday: 9:00 AM – 4:00 PM / Friday: 9:00 AM – 4:00 PM / Saturday: Closed / Sunday: Closed",
    "last_verified": "2026-03-28",
    "status": "unverified",
    "source": "google_maps",
    "place_id": "ChIJnzJlxbQv2jARwIm02opYGHA",
    "priority": 0,
    "ai_reviewed": true
  },
  {
    "slug": "his-chiang-mai",
    "name": "HIS Chiang Mai",
    "name_ja": "HIS チェン マイ",
    "area": "Chiang Mai",
    "address": "Duangtawan Hotel Chiang Mai Room number G4 132 Loi Kroh Rd, Tambon Chang Khlan, Amphoe Mueang Chiang Mai, Chang Wat Chiang Mai 50100, Thailand",
    "lat": 18.7837,
    "lng": 98.9991,
    "phone": "+6653214263",
    "website": "http://www.his-bkk.com/",
    "description": "日本の大手旅行会社HISのチェンマイ支店。日本行き航空券・ツアーの手配、チェンマイ発の現地ツアーを日本語で対応",
    "tags": [
      "旅行",
      "ツアー",
      "日本語対応"
    ],
    "hours": "Monday: 9:00 AM – 6:00 PM / Tuesday: 9:00 AM – 6:00 PM / Wednesday: 9:00 AM – 6:00 PM / Thursday: 9:00 AM – 6:00 PM / Friday: 9:00 AM – 6:00 PM / Saturday: Closed / Sunday: Closed",
    "last_verified": "2026-03-28",
    "status": "unverified",
    "source": "google_maps",
    "place_id": "ChIJScSgHmM62jARihPJr47nj4c",
    "priority": 0,
    "ai_reviewed": true
  },
  {
    "slug": "cm",
    "name": "CMランナーツアー",
    "name_ja": "CMランナーツアー",
    "area": "Chiang Mai",
    "address": "144, 1 Loi Kroh Rd, Tambon Chang Moi, Amphoe Mueang Chiang Mai, Chang Wat Chiang Mai 50100, Thailand",
    "lat": 18.7839,
    "lng": 99.0018,
    "phone": "+6653276643",
    "website": "http://chiangmaitravel.jp/",
    "description": "チェンマイを拠点とする日系ツアー会社。北部タイの観光・トレッキング・ゴルフツアーを日本語ガイド付きで催行、日本語サイトあり",
    "tags": [
      "旅行",
      "ツアー",
      "日本語対応"
    ],
    "hours": "Monday: 9:00 AM – 4:00 PM / Tuesday: 9:00 AM – 4:00 PM / Wednesday: 9:00 AM – 4:00 PM / Thursday: 9:00 AM – 4:00 PM / Friday: 9:00 AM – 4:00 PM / Saturday: Closed / Sunday: Closed",
    "last_verified": "2026-03-28",
    "status": "unverified",
    "source": "google_maps",
    "place_id": "ChIJVYh1JqY62jARkt1KZClMIfw",
    "priority": 0,
    "ai_reviewed": true
  },
  {
    "slug": "phuket-gold-travel",
    "name": "Phuket Gold Travel プーケットゴールドトラベル",
    "name_ja": "プーケットゴールドトラベル",
    "area": "Phuket",
    "address": "Thailand, Phuket, Mueang Phuket District, Wichit, 22/83 Moo.2 Supalai Ville Tep-a-nu-son Village",
    "lat": 7.8641,
    "lng": 98.3617,
    "phone": "+66928926642",
    "website": "http://phuketgoldtravel.jp/",
    "description": "プーケットを拠点とする日系旅行会社。島内ツアー・離島ツアー・空港送迎・ゴルフ手配を日本語で対応、日本語サイトあり",
    "tags": [
      "旅行",
      "ツアー",
      "日本語対応"
    ],
    "hours": "Monday: 8:00 AM – 9:00 PM / Tuesday: 8:00 AM – 9:00 PM / Wednesday: 8:00 AM – 9:00 PM / Thursday: 8:00 AM – 9:00 PM / Friday: 8:00 AM – 9:00 PM / Saturday: 8:00 AM – 9:00 PM / Sunday: 8:00 AM – 9:00 PM",
    "last_verified": "2026-03-28",
    "status": "unverified",
    "source": "google_maps",
    "place_id": "ChIJdwx0Z7ovUDAR6GKDWx56S7k",
    "priority": 0,
    "ai_reviewed": true
  },
  {
    "slug": "j-and-r-agency-co-ltd",
    "name": "J & R Agency Co.,Ltd.",
    "name_ja": "J & R エージェンシー Co.,Ltd.",
    "area": "Phuket",
    "address": "135/19 Rat -U-Thid, 200 Pi Road, ตำบลป่าตอง อำเภอกะทู้ ภูเก็ต 83150, Thailand",
    "lat": 7.8952,
    "lng": 98.2997,
    "phone": "+6676344093",
    "website": "http://www.jandrphuket.com/",
    "description": "プーケットの日系旅行代理店。プーケット島内ツアー・マリンアクティビティ・空港送迎を日本語で手配、現地在住者にも対応",
    "tags": [
      "旅行",
      "ツアー",
      "日本語対応"
    ],
    "hours": "Monday: 10:00 AM – 6:00 PM / Tuesday: 10:00 AM – 6:00 PM / Wednesday: 10:00 AM – 6:00 PM / Thursday: 10:00 AM – 6:00 PM / Friday: 10:00 AM – 6:00 PM / Saturday: 10:00 AM – 6:00 PM / Sunday: Closed",
    "last_verified": "2026-03-28",
    "status": "unverified",
    "source": "google_maps",
    "place_id": "ChIJNW_eE6M6UDARRIlCl-6REKk",
    "priority": 0,
    "ai_reviewed": true
  },
  {
    "slug": "phuket-happy-tour",
    "name": "Phuket Happy Tour",
    "name_ja": "プーケット ハッピー ツアー",
    "area": "Phuket",
    "address": "135/11 Paradise complex Rat-u-tid R,d, Patong Beach,, ตำบลป่าตอง Patong Beach, Phuket 83150, Thailand",
    "lat": 7.8951,
    "lng": 98.2995,
    "phone": "+66956239266",
    "website": "https://phukethappytour.com/",
    "description": "プーケットの現地ツアー・アクティビティを手がける旅行会社。離島ツアー・シュノーケリング・空港送迎などを日本語で予約可能",
    "tags": [
      "旅行",
      "ツアー",
      "日本語対応"
    ],
    "hours": "Monday: 9:00 AM – 9:00 PM / Tuesday: 9:00 AM – 9:00 PM / Wednesday: 9:00 AM – 9:00 PM / Thursday: 9:00 AM – 9:00 PM / Friday: 9:00 AM – 9:00 PM / Saturday: 9:00 AM – 9:00 PM / Sunday: 9:00 AM – 9:00 PM",
    "last_verified": "2026-03-28",
    "status": "unverified",
    "source": "google_maps",
    "place_id": "ChIJJ8pGSas7UDAR7pFJKla92fM",
    "priority": 0,
    "ai_reviewed": true
  },
  {
    "slug": "hobo-ya-similan",
    "name": "Hobo-ya Similan",
    "name_ja": "ほぼ屋 シミラン",
    "area": "Phuket",
    "address": "135, 31 Moo4, Tambon Rawai, Amphoe Mueang Phuket, Chang Wat Phuket 83130, Thailand",
    "lat": 7.8225,
    "lng": 98.3376,
    "phone": "+6676280284",
    "website": "http://www.hobo-ya-similan.com/",
    "description": "シミラン諸島ダイビング・シュノーケリングツアーを専門とする日系ツアー会社「ほぼ屋」。プーケット発、日本語ガイド付きで催行",
    "tags": [
      "旅行",
      "ツアー",
      "日本語対応"
    ],
    "hours": "Monday: 9:00 AM – 6:00 PM / Tuesday: 9:00 AM – 6:00 PM / Wednesday: 9:00 AM – 6:00 PM / Thursday: 9:00 AM – 6:00 PM / Friday: 9:00 AM – 6:00 PM / Saturday: 9:00 AM – 6:00 PM / Sunday: 9:00 AM – 6:00 PM",
    "last_verified": "2026-03-28",
    "status": "unverified",
    "source": "google_maps",
    "place_id": "ChIJTcNh4VMwUDARWBZKyeX52VA",
    "priority": 0,
    "ai_reviewed": true
  },
  {
    "slug": "krabi-sakura-tour",
    "name": "Krabi Sakura Tour",
    "name_ja": "クラビ サクラ ツアー",
    "area": "Phuket",
    "address": "25 ถนนอิศรา Tambon Pak Nam, Amphoe Mueang Krabi, Chang Wat Krabi 81000, Thailand",
    "lat": 8.0624,
    "lng": 98.9171,
    "phone": "+6675622262",
    "website": "https://krabisakuratour.com/",
    "description": "クラビ地方の現地ツアーを手がける旅行会社。クラビ・ピピ島・ランタ島へのツアー・送迎を手配、日本語対応で予約可能",
    "tags": [
      "旅行",
      "ツアー",
      "日本語対応"
    ],
    "hours": "Monday: 9:00 AM – 9:00 PM / Tuesday: 9:00 AM – 9:00 PM / Wednesday: 9:00 AM – 9:00 PM / Thursday: 9:00 AM – 9:00 PM / Friday: 9:00 AM – 9:00 PM / Saturday: 9:00 AM – 9:00 PM / Sunday: 9:00 AM – 9:00 PM",
    "last_verified": "2026-03-28",
    "status": "unverified",
    "source": "google_maps",
    "place_id": "ChIJwVYmDJmUUTARIYTUB7Jwras",
    "priority": 0,
    "ai_reviewed": true
  },
  {
    "slug": "phuket-ryoko-co-ltd",
    "name": "プーケット旅行センター(Phuket Ryoko Co.,Ltd)",
    "name_ja": "プーケット旅行センター",
    "area": "Phuket",
    "address": "Thailand, Phuket, Kathu District, Phuket 135/20 Paradise Complex ,Rat-U-Thit 200 Road, Patong Beach, Kathu",
    "lat": 7.8948,
    "lng": 98.2999,
    "phone": "+6676346123",
    "website": "https://www.phuket-ryoko.com/",
    "description": "プーケットの老舗日系旅行センター。島内観光・離島ツアー・空港送迎・ホテル予約を日本語でワンストップ対応、現地在住者にも対応",
    "tags": [
      "旅行",
      "ツアー",
      "日本語対応"
    ],
    "hours": null,
    "last_verified": "2026-03-28",
    "status": "unverified",
    "source": "google_maps",
    "place_id": "ChIJzdFIEKM6UDAR7IWCq2fOtI4",
    "priority": 0,
    "ai_reviewed": true
  },
  {
    "slug": "hobo-ya-phuket",
    "name": "Hobo-ya Phuket",
    "name_ja": "ほぼ屋 プーケット",
    "area": "Phuket",
    "address": "135/31,Moo4, Patak Villa Soi1, Rawai, Phuket 83130, Thailand",
    "lat": 7.8224,
    "lng": 98.3374,
    "phone": "+6676280282",
    "website": "http://www.houbou-ya-phuket.com/",
    "description": "プーケットを拠点とする日系ツアー会社「ほぼ屋」。ダイビング・シュノーケリング・離島ツアーを日本語ガイド付きで催行",
    "tags": [
      "旅行",
      "ツアー",
      "日本語対応"
    ],
    "hours": "Monday: 9:00 AM – 6:00 PM / Tuesday: 9:00 AM – 6:00 PM / Wednesday: 9:00 AM – 6:00 PM / Thursday: 9:00 AM – 6:00 PM / Friday: 9:00 AM – 6:00 PM / Saturday: 9:00 AM – 6:00 PM / Sunday: 9:00 AM – 6:00 PM",
    "last_verified": "2026-03-28",
    "status": "unverified",
    "source": "google_maps",
    "place_id": "ChIJdRoIHw4vUDARkHQ2pKY_6D0",
    "priority": 0,
    "ai_reviewed": true
  },
  {
    "slug": "taxi-mr-kai-phuket-mr-mr-kai",
    "name": "Taxi mr.kai-phuket タクシー mr.ガイープケット такси кай خدمة سيارات الأجرةMr.kai שירותי מוניות מר קאי",
    "name_ja": "タクシー ガイープケット",
    "area": "Phuket",
    "address": "93 Muen-Ngern Rd, Tambon Patong, Amphoe Kathu, Chang Wat Phuket 83150, Thailand",
    "lat": 7.884,
    "lng": 98.2742,
    "phone": "+66818935152",
    "website": "https://www.kaitaxiandtour.com/",
    "description": "プーケットの日本語対応タクシー・送迎サービス。空港送迎・島内観光・チャーターを日本語で予約可能、個人旅行者に便利",
    "tags": [
      "旅行",
      "ツアー",
      "日本語対応"
    ],
    "hours": "Monday: 6:00 AM – 11:00 PM / Tuesday: 6:00 AM – 11:00 PM / Wednesday: 6:00 AM – 11:00 PM / Thursday: 6:00 AM – 11:00 PM / Friday: 6:00 AM – 11:00 PM / Saturday: 6:00 AM – 11:00 PM / Sunday: 6:00 AM – 11:00 PM",
    "last_verified": "2026-03-28",
    "status": "unverified",
    "source": "google_maps",
    "place_id": "ChIJMfKbvsk7UDAR6OFPNUFhe-k",
    "priority": 0,
    "ai_reviewed": true
  },
  {
    "slug": "blue-island",
    "name": "Blue Island",
    "name_ja": "ブルー アイランド",
    "area": "Phuket",
    "address": "68 63 soi 12 maneekram Tambon Chalong, phuket Chang Wat Phuket 83130, Thailand",
    "lat": 7.8565,
    "lng": 98.3501,
    "phone": "+66819702156",
    "website": "https://www.blueisland-phuket.com/",
    "description": "プーケットのマリンアクティビティ・離島ツアーを手がける旅行会社。ピピ島・コーラル島ツアーなどを日本語で予約可能",
    "tags": [
      "旅行",
      "ツアー",
      "日本語対応"
    ],
    "hours": "Monday: 9:00 AM – 6:00 PM / Tuesday: 9:00 AM – 6:00 PM / Wednesday: 9:00 AM – 6:00 PM / Thursday: 9:00 AM – 6:00 PM / Friday: 9:00 AM – 6:00 PM / Saturday: 9:00 AM – 12:00 PM / Sunday: Closed",
    "last_verified": "2026-03-28",
    "status": "unverified",
    "source": "google_maps",
    "place_id": "ChIJXRED5JcxUDARXbIHnMSFr7U",
    "priority": 0,
    "ai_reviewed": true
  },
  {
    "slug": "yaya",
    "name": "yaya",
    "name_ja": "ヤヤ",
    "area": "Pattaya",
    "address": "181, 4 Pattayaklang 12-6, Muang Pattaya, Amphoe Bang Lamung, Chang Wat Chon Buri 20150, Thailand",
    "lat": 12.9357,
    "lng": 100.8895,
    "phone": "+66985033402",
    "website": null,
    "description": "パタヤの現地旅行・観光サポートサービス。パタヤ周辺のツアー・アクティビティ・送迎の手配に対応、日本語でのコミュニケーション可能",
    "tags": [
      "旅行",
      "ツアー",
      "日本語対応"
    ],
    "hours": "Monday: 10:00 AM – 10:00 PM / Tuesday: 10:00 AM – 6:00 PM / Wednesday: 10:00 AM – 10:00 PM / Thursday: 10:00 AM – 10:00 PM / Friday: 10:00 AM – 10:00 PM / Saturday: 10:00 AM – 12:00 AM / Sunday: 10:00 AM – 12:00 AM",
    "last_verified": "2026-03-28",
    "status": "unverified",
    "source": "google_maps",
    "place_id": "ChIJpy8ncTeVAjERufYFKLFm6eA",
    "priority": 0,
    "ai_reviewed": true
  },
  {
    "slug": "p",
    "name": "p",
    "name_ja": "p",
    "area": "Pattaya",
    "address": "502/44 หมู่.10 ตำบล หนองปรือ, เมืองพัทยา อำเภอบางละมุง ชลบุรี 20150, Thailand",
    "lat": 12.9311,
    "lng": 100.8848,
    "phone": null,
    "website": null,
    "description": "パタヤの現地旅行・観光サポートサービス。パタヤ周辺のツアーや観光スポット巡り・送迎の手配に対応、在住者や旅行者をサポート",
    "tags": [
      "旅行",
      "ツアー",
      "日本語対応"
    ],
    "hours": "Monday: 10:00 AM – 11:00 PM / Tuesday: 10:00 AM – 11:00 PM / Wednesday: 10:00 AM – 11:00 PM / Thursday: 10:00 AM – 11:00 PM / Friday: 10:00 AM – 11:00 PM / Saturday: 10:00 AM – 11:00 PM / Sunday: Closed",
    "last_verified": "2026-03-28",
    "status": "unverified",
    "source": "google_maps",
    "place_id": "ChIJ1QC6qQqXAjERz8V9FOY8Vco",
    "priority": 0,
    "ai_reviewed": true
  },
  {
    "slug": "all-pattaya",
    "name": "オールパタヤ(All Pattaya)",
    "name_ja": "オールパタヤ",
    "area": "Pattaya",
    "address": "555 56 Thanon Pattayasaisong, Muang Pattaya, Amphoe Bang Lamung, Chang Wat Chon Buri 20150, Thailand",
    "lat": 12.9285,
    "lng": 100.8782,
    "phone": "+6638429610",
    "website": "http://all-pattaya.com/",
    "description": "パタヤの日系旅行情報・ツアー手配サービス「オールパタヤ」。パタヤ在住日本人向けにツアー・送迎・生活情報を日本語で提供",
    "tags": [
      "旅行",
      "ツアー",
      "日本語対応"
    ],
    "hours": "Monday: 10:00 AM – 6:00 PM / Tuesday: 10:00 AM – 6:00 PM / Wednesday: 10:00 AM – 6:00 PM / Thursday: 10:00 AM – 6:00 PM / Friday: 10:00 AM – 6:00 PM / Saturday: 10:00 AM – 6:00 PM / Sunday: 10:00 AM – 6:00 PM",
    "last_verified": "2026-03-28",
    "status": "unverified",
    "source": "google_maps",
    "place_id": "ChIJt3LcK4yXAjERGULVS-QjpEU",
    "priority": 0,
    "ai_reviewed": true
  },
  {
    "slug": "k-n-taxitour-co-ltd",
    "name": "K.N.TAXITOUR CO.,LTD.",
    "name_ja": "K.N.タクシーツアー",
    "area": "Pattaya",
    "address": "1, 11, Tambon Nong Pla Lai, Amphoe Bang Lamung, Chang Wat Chon Buri 20150, Thailand",
    "lat": 12.9838,
    "lng": 100.937,
    "phone": "+66991053080",
    "website": "https://page.line.me/kntaxitour",
    "description": "パタヤ・シラチャ地区の日本語対応タクシー・送迎サービス。空港送迎・観光チャーター・ゴルフ送迎をLINEで予約可能",
    "tags": [
      "旅行",
      "ツアー",
      "日本語対応"
    ],
    "hours": "Monday: 9:00 AM – 10:00 PM / Tuesday: 9:00 AM – 10:00 PM / Wednesday: 9:00 AM – 10:00 PM / Thursday: 9:00 AM – 10:00 PM / Friday: 9:00 AM – 10:00 PM / Saturday: 9:00 AM – 10:00 PM / Sunday: 9:00 AM – 10:00 PM",
    "last_verified": "2026-03-28",
    "status": "unverified",
    "source": "google_maps",
    "place_id": "ChIJf4-efGm_AjERAFTpOAYfZWg",
    "priority": 0,
    "ai_reviewed": true
  },
  {
    "slug": "his-sriracha",
    "name": "HIS Sriracha",
    "name_ja": "HIS シラチャ",
    "area": "Pattaya",
    "address": "60 Sriracha Nakorn 3 Road, Sriracha, Chon Buri 20110, Thailand",
    "lat": 13.169,
    "lng": 100.9297,
    "phone": "+6638323500",
    "website": "http://www.his-bkk.com/",
    "description": "日本の大手旅行会社HISのシラチャ支店。日本行き航空券・ツアーの手配を日本語で対応、シラチャ・パタヤ在住日本人に便利",
    "tags": [
      "旅行",
      "ツアー",
      "日本語対応"
    ],
    "hours": "Monday: 9:30 AM – 6:00 PM / Tuesday: 9:30 AM – 6:00 PM / Wednesday: Closed / Thursday: 9:30 AM – 6:00 PM / Friday: 9:30 AM – 6:00 PM / Saturday: 9:30 AM – 6:00 PM / Sunday: 9:30 AM – 6:00 PM",
    "last_verified": "2026-03-28",
    "status": "unverified",
    "source": "google_maps",
    "place_id": "ChIJ_apE7QG3AjERuBXREM_lVy8",
    "priority": 0,
    "ai_reviewed": true
  },
  {
    "slug": "soi-taxi-pattaya",
    "name": "Soi Taxi Pattaya",
    "name_ja": "ソイ タクシー パタヤ",
    "area": "Pattaya",
    "address": "88 91 เพนียดช้าง Muang Pattaya, Amphoe Bang Lamung, Chang Wat Chon Buri 20150, Thailand",
    "lat": 12.9434,
    "lng": 100.9012,
    "phone": "+66925256744",
    "website": "https://www.soitaxi.com/",
    "description": "パタヤの日本語対応タクシー・チャーターサービス。空港送迎・観光ツアー・ゴルフ送迎をオンライン予約可能、定額料金で安心",
    "tags": [
      "旅行",
      "ツアー",
      "日本語対応"
    ],
    "hours": "Monday: Open 24 hours / Tuesday: Open 24 hours / Wednesday: Open 24 hours / Thursday: Open 24 hours / Friday: Open 24 hours / Saturday: Open 24 hours / Sunday: Open 24 hours",
    "last_verified": "2026-03-28",
    "status": "unverified",
    "source": "google_maps",
    "place_id": "ChIJl1CRozGVAjER2vapKM278To",
    "priority": 0,
    "ai_reviewed": true
  }
]