[
  {
    "slug": "matchado-chiswick",
    "name": "MATCHADO Chiswick",
    "name_ja": "抹茶堂 チズウィック店",
    "area": "Chiswick",
    "address": "5 Chiswick Common Road, Chiswick, London W4 1RR",
    "lat": null,
    "lng": null,
    "phone": null,
    "website": "https://matchado.co.uk/",
    "description": "日本人が創業した抹茶専門カフェ。宇治抹茶・焙じ茶を使用したドリンクとスイーツを提供。卸売にも対応。Kings Cross店もあり。",
    "tags": ["抹茶", "日本茶", "スイーツ", "日本人経営"],
    "hours": "Mon-Fri 8:00-17:00, Sat-Sun 9:00-17:00",
    "last_verified": "2026-03-28",
    "status": "unverified",
    "source": "web_search",
    "place_id": "",
    "priority": 0,
    "ai_reviewed": true
  },
  {
    "slug": "tsujiri-chinatown",
    "name": "Tsujiri Chinatown",
    "name_ja": "辻利 チャイナタウン店",
    "area": "Chinatown",
    "address": "33 Newport Court, London WC2H 7PQ",
    "lat": null,
    "lng": null,
    "phone": null,
    "website": "https://www.tsujiri.co.uk/",
    "description": "1860年京都・宇治創業の老舗茶舗「辻利」のロンドン店。抹茶アイスクリーム、抹茶ラテ、日本茶を提供。Camden店もあり。",
    "tags": ["抹茶", "アイスクリーム", "日本茶", "老舗"],
    "hours": null,
    "last_verified": "2026-03-28",
    "status": "unverified",
    "source": "web_search",
    "place_id": "",
    "priority": 0,
    "ai_reviewed": true
  },
  {
    "slug": "tsujiri-camden",
    "name": "Tsujiri Camden",
    "name_ja": "辻利 カムデン店",
    "area": "Camden",
    "address": "Unit 163, Water Lane, Hawley Wharf, London NW1 8JZ",
    "lat": null,
    "lng": null,
    "phone": null,
    "website": "https://www.tsujiri.co.uk/",
    "description": "1860年京都・宇治創業の老舗茶舗「辻利」のCamden Market店。宇治抹茶を使用したドリンクとデザートを提供。",
    "tags": ["抹茶", "アイスクリーム", "日本茶", "老舗"],
    "hours": null,
    "last_verified": "2026-03-28",
    "status": "unverified",
    "source": "web_search",
    "place_id": "",
    "priority": 0,
    "ai_reviewed": true
  },
  {
    "slug": "how-matcha-marylebone",
    "name": "How Matcha!",
    "name_ja": "ハウマッチャ",
    "area": "Marylebone",
    "address": "47 Blandford Street, Marylebone, London W1U 7HQ",
    "lat": null,
    "lng": null,
    "phone": "+442080973615",
    "website": "https://howmatcha.com/",
    "description": "Marylebone発の抹茶カフェ。鹿児島産のセレモニアルグレード抹茶を使用。抹茶ラテ、抹茶ケーキ、抹茶ブラウニーなどを提供。風水を取り入れた店内デザイン。Notting Hill店もあり。",
    "tags": ["抹茶", "カフェ", "鹿児島産抹茶"],
    "hours": null,
    "last_verified": "2026-03-28",
    "status": "unverified",
    "source": "web_search",
    "place_id": "",
    "priority": 0,
    "ai_reviewed": true
  },
  {
    "slug": "wa-cafe-covent-garden",
    "name": "WA Cafe",
    "name_ja": "WAカフェ コヴェントガーデン店",
    "area": "Covent Garden",
    "address": "5 New Row, London WC2N 4LH",
    "lat": null,
    "lng": null,
    "phone": "+442072405567",
    "website": "https://www.wacafe.co.uk/",
    "description": "日本人パン職人・パティシエが毎日焼き上げる日本式パン・菓子の専門店。メロンパン、あんぱん、桜ティラミスなど日本の製パン技術を活かした商品を提供。Ealing Broadway、Marylebone、Aldgate East店もあり。抹茶・焙じ茶パウダーも販売。",
    "tags": ["パティスリー", "日本式パン", "抹茶スイーツ", "日本人職人"],
    "hours": null,
    "last_verified": "2026-03-28",
    "status": "unverified",
    "source": "web_search",
    "place_id": "",
    "priority": 0,
    "ai_reviewed": true
  },
  {
    "slug": "katsute100-camden",
    "name": "Katsute 100",
    "name_ja": "かつて100",
    "area": "Camden",
    "address": "100 Camden High Street, London NW1 0LU",
    "lat": null,
    "lng": null,
    "phone": null,
    "website": "https://www.katsute100.com/",
    "description": "日本茶専門カフェ。玉露、抹茶、煎茶などの日本茶と和菓子を提供。築100年以上の建物をリノベーションした店舗。",
    "tags": ["日本茶", "和菓子", "抹茶"],
    "hours": null,
    "last_verified": "2026-03-28",
    "status": "unverified",
    "source": "web_search",
    "place_id": "",
    "priority": 0,
    "ai_reviewed": true
  },
  {
    "slug": "tombo-south-kensington",
    "name": "Tombo",
    "name_ja": "トンボ",
    "area": "South Kensington",
    "address": "29 Thurloe Place, London SW7 2HQ",
    "lat": null,
    "lng": null,
    "phone": "+442075893775",
    "website": "https://www.tombocafe.com/",
    "description": "サウスケンジントンにある日本式カフェ。日本のカレー、おにぎり、抹茶ラテ、日本のケーキを提供。South Kensington駅から徒歩1分。",
    "tags": ["カフェ", "カレー", "おにぎり", "抹茶"],
    "hours": null,
    "last_verified": "2026-03-28",
    "status": "unverified",
    "source": "web_search",
    "place_id": "",
    "priority": 0,
    "ai_reviewed": true
  },
  {
    "slug": "wa-cafe-ealing",
    "name": "WA Cafe Ealing",
    "name_ja": "WAカフェ イーリング店",
    "area": "Ealing Broadway",
    "address": "16 The Mall, Ealing, London W5 2PJ",
    "lat": null,
    "lng": null,
    "phone": null,
    "website": "https://www.wacafe.co.uk/",
    "description": "日本人パン職人・パティシエが毎日焼き上げる日本式パン・菓子の専門店のイーリング店。日本人が多く住むイーリングエリアに位置。",
    "tags": ["パティスリー", "日本式パン", "抹茶スイーツ", "日本人職人"],
    "hours": null,
    "last_verified": "2026-03-28",
    "status": "unverified",
    "source": "web_search",
    "place_id": "",
    "priority": 0,
    "ai_reviewed": true
  },
  {
    "slug": "matchado-kings-cross",
    "name": "MATCHADO Kings Cross",
    "name_ja": "抹茶堂 キングスクロス店",
    "area": "Kings Cross",
    "address": "Coal Drops Yard, Stable Street, London N1C 4DQ",
    "lat": null,
    "lng": null,
    "phone": null,
    "website": "https://matchado.co.uk/",
    "description": "抹茶堂のKings Cross店。Coal Drops Yard内に位置。宇治抹茶・焙じ茶を使用したドリンク・スイーツを提供。",
    "tags": ["抹茶", "日本茶", "スイーツ", "日本人経営"],
    "hours": null,
    "last_verified": "2026-03-28",
    "status": "unverified",
    "source": "web_search",
    "place_id": "",
    "priority": 0,
    "ai_reviewed": true
  }
]
