[
  {
    "slug": "blake-cassels-legal-toronto",
    "name": "Blake, Cassels & Graydon LLP",
    "name_ja": "ブレイク・カッセルズ・グレイドン法律事務所",
    "area": "Toronto",
    "address": "199 Bay Street, Suite 2500, Toronto, ON M5L 1A9",
    "phone": "+1-416-863-2500",
    "phone_local": null,
    "email": null,
    "website": "https://www.blakecassels.com",
    "source_url": "https://www.blakecassels.com",
    "description": "Toronto の大手法律事務所。移民・ビザサポート。",
    "detail": "Blake, Cassels & Graydon LLPはTorontoの大手国際法律事務所。移民法・ビザサポート・事業法律など多岐に対応。日本人駐在員のビザ問題に対応経験豊富。",
    "menu": null,
    "price_range": null,
    "tags": [
      "legal"
    ],
    "hours": null,
    "status": "verified",
    "last_verified": "2026-04-06",
    "source": "web_search",
    "place_id": "",
    "priority": 0,
    "ai_reviewed": true,
    "rating": null,
    "user_rating_count": null,
    "price_level": null,
    "photo_name": null
  },
  {
    "slug": "hara-company-burnaby",
    "name": "Hara & Company Law Corp",
    "name_ja": "原法律事務所",
    "area": "Burnaby",
    "address": "4664 Lougheed Hwy. #155, Burnaby, BC V5C 5T5, Canada",
    "phone": "+16042554800",
    "phone_local": null,
    "email": "info@haraco.ca",
    "website": "https://haraco.ca/",
    "source_url": "https://haraco.ca/about-us/",
    "description": "1962年創業・バーナビーの日系法律事務所。BC州初の日系カナダ人弁護士として開業した老舗で、会社法・不動産・遺産・家事・民事訴訟を日本語で60年以上サポート。",
    "detail": "1962年創業のバーナビーに位置する老舗日系法律事務所。BC州初の日系カナダ人弁護士による法律事務所として知られ、60年以上にわたって在バンクーバー日本人コミュニティの法律ニーズに対応してきた。会社法・民事訴訟・不動産・遺言・遺産管理・家事法など幅広い分野を日本語・英語でサポート。",
    "menu": null,
    "price_range": null,
    "tags": [
      "日系法律事務所",
      "老舗1962年",
      "Burnaby",
      "日本語対応"
    ],
    "hours": null,
    "status": "unverified",
    "last_verified": "2026-04-05",
    "source": "web_search",
    "place_id": "",
    "priority": 0,
    "ai_reviewed": true,
    "rating": null,
    "user_rating_count": null,
    "price_level": null,
    "photo_name": null
  },
  {
    "slug": "toronto-immigration-law-firm",
    "name": "Toronto Immigration Law Firm",
    "name_ja": "トロント移民法律事務所",
    "area": "Toronto",
    "address": "220 Bay Street, Suite 1400, Toronto, ON M5J 2W4",
    "phone": "+1-416-366-5500",
    "phone_local": null,
    "email": null,
    "website": "https://www.torontoimmigrationlaw.ca/",
    "source_url": "https://www.torontoimmigrationlaw.ca/",
    "description": "トロントの移民法専門事務所。ワークビザ・永住権・家族再統一手続を日本人駐在員向けにサポート。",
    "detail": "トロントの移民法専門事務所。ワークパーミット取得、永住権申請、ファミリースポンサーシップ、市民権申請などを専門に扱う。日本人駐在員・起業家・学生向けの移民手続をサポート。英語対応。",
    "menu": null,
    "price_range": null,
    "tags": [
      "移民法",
      "Toronto",
      "ワークビザ"
    ],
    "hours": null,
    "status": "unverified",
    "last_verified": "2026-04-06",
    "source": "website",
    "place_id": "",
    "priority": 0,
    "ai_reviewed": true,
    "rating": null,
    "user_rating_count": null,
    "price_level": null,
    "photo_name": null
  }
]