[
  {
    "slug": "ferrys-munich",
    "name": "Ferry's Japanese Hair Salon",
    "name_ja": "フェリーズ 日本式ヘアサロン",
    "area": "München, Isarvorstadt",
    "address": "Reichenbachstraße 15, 80469 München",
    "lat": 48.1334,
    "lng": 11.5748,
    "phone": "+498922 2757",
    "phone_local": "089 222757",
    "email": "kontakt@hairferry.de",
    "website": "https://hairferry.de",
    "description": "ミュンヘンの日本式ヘアサロン。スタッフ全員が日本人で、ミルボン公認サロンとしてアジア系の髪質に精通。縮毛矯正・カラー・ヘッドスパ対応。日独英3言語可。",
    "detail": "ミュンヘン・イザールフォアシュタットの中庭に位置する日本式ヘアサロン。スタッフ全員が日本人で、日本・ドイツ・アメリカ・中国でキャリアを積んだ経験豊富なスタイリストが揃う。日本のMilbonブランドのパートナーサロンとして、ハイエンドな日本式ヘアケア製品を使用。縮毛矯正・パーマ・カラーリング・ヘッドスパ・カットに対応。日本語・ドイツ語・英語での相談が可能で、在独日本人・アジア系の方にも幅広く利用されている。",
    "tags": [
      "ヘアサロン",
      "日本人スタッフ",
      "縮毛矯正",
      "ミルボン",
      "ミュンヘン"
    ],
    "hours": "09:30-19:00 / 09:30-19:00 / 09:00-19:00 / 09:00-19:00 / 09:00-19:00 / 09:00-18:30 / closed",
    "last_verified": "2026-04-07",
    "status": "unverified",
    "source": "web_search",
    "place_id": "",
    "priority": 5,
    "ai_reviewed": true,
    "place_reviewed": true,
    "japanese_staff": true,
    "rating": null,
    "user_rating_count": null,
    "price_level": null,
    "photo_name": null
  },
  {
    "slug": "friseur-mirage",
    "name": "Friseur Mirage",
    "name_ja": "フリズール ミラージュ",
    "area": "Düsseldorf, Stadt-Mitte",
    "address": "Kreuzstraße 17, 40210 Düsseldorf",
    "lat": null,
    "lng": null,
    "phone": "+4921117542975",
    "phone_local": "0211 17542975",
    "email": null,
    "website": "https://mirage-duesseldorf.com",
    "description": "東京でキャリアを積んだオーナーが2011年に開業したデュッセルドルフの日本式ヘアサロン。日本式ヘッドスパ・カット・カラー・縮毛矯正に対応。ウェブサイトに日本語ページあり。",
    "detail": "オーナーが東京でヘアサロンキャリアを積んだ後、2010年に渡独し2011年2月に開業した日本式プレミアムヘアサロン。日本式ヘッドスパ・スカルプケアを主力サービスとし、カット・カラーリング・縮毛矯正にも対応。MILBON・Nevitalyなどのプレミアム製品を使用。ウェブサイトに日本語ページがあり、日本語での相談が可能。月〜金10:00-19:00、土10:00-18:00営業。完全予約制（電話・メールのみ受付）。",
    "tags": [
      "ヘアサロン",
      "日本式ヘッドスパ",
      "縮毛矯正",
      "日本語対応",
      "デュッセルドルフ"
    ],
    "hours": "月〜金 10:00-19:00 / 土 10:00-18:00",
    "last_verified": "2026-04-07",
    "status": "unverified",
    "source": "web_search",
    "place_id": "",
    "priority": 5,
    "ai_reviewed": true,
    "place_reviewed": true,
    "japanese_staff": true,
    "rating": null,
    "user_rating_count": null,
    "price_level": null,
    "photo_name": null
  },
  {
    "slug": "ginza-matsunaga-frankfurt",
    "name": "Ginza Matsunaga Frankfurt",
    "name_ja": "銀座マツナガ フランクフルト",
    "area": "Frankfurt, Innenstadt",
    "address": "Große Bockenheimer Str. 21, 60313 Frankfurt am Main",
    "lat": null,
    "lng": null,
    "phone": "+496929671 2",
    "phone_local": "069 296712",
    "email": "ginzamatsunagaffm@gmail.com",
    "website": "https://ginza-matsunaga.com/en/home/",
    "description": "1985年創業のフランクフルト老舗日本式ヘアサロン。東京で修行したスタイリストが定期的に来独し、最新の日本式カット・カラー・パーマ・ネイル・マッサージを提供。",
    "detail": "1985年にフランクフルトで開業した銀座マツナガの欧州拠点。東京の銀座松永グループからスタイリストが定期的に来独し、最新の日本式トレンドと技術をもたらす。カット・パーマ・カラーのほか、ネイルデザイン・まつ毛パーマ・シアツーマッサージ・フェイストリートメントも対応。在独日本人から長年の信頼を得ており、予約は電話のみ受付（フランクフルト店）。ハンブルク店（Stadthausbrücke 5）も展開中。",
    "tags": [
      "ヘアサロン",
      "日本人スタイリスト",
      "フランクフルト",
      "ネイル",
      "マッサージ"
    ],
    "hours": null,
    "last_verified": "2026-04-07",
    "status": "unverified",
    "source": "web_search",
    "place_id": "",
    "priority": 4,
    "ai_reviewed": true,
    "place_reviewed": true,
    "japanese_staff": true,
    "rating": null,
    "user_rating_count": null,
    "price_level": null,
    "photo_name": null
  },
  {
    "slug": "ginza-matsunaga-hamburg",
    "name": "Ginza Matsunaga Hamburg",
    "name_ja": "銀座マツナガ ハンブルク",
    "area": "Hamburg, Neustadt",
    "address": "Stadthausbrücke 5, 20355 Hamburg",
    "lat": null,
    "lng": null,
    "phone": "+4904037519759",
    "phone_local": "040 37519759",
    "email": null,
    "website": "http://hairsalon-ginza-matsunaga.de/index_en.html",
    "description": "1995年開業の銀座マツナガ・ハンブルク店。東京修行のスタイリストによるカット・カラー・パーマのほかネイル・まつ毛パーマ・シアツーマッサージも提供。",
    "detail": "1995年にオープンした銀座マツナガのハンブルク拠点。東京で訓練を受けたスタイリストが定期的に入れ替わりながら最新の日本式スタイルを提供する。カット・カラー・パーマに加え、ネイルデザイン・まつ毛パーマ・シアツーマッサージ・フェイストリートメント・ツボンフットマッサージも対応。Sバーン「Stadthausbrücke」駅から徒歩約5分のアクセス良好な立地。月〜金10:00-19:00、土10:00-18:00。",
    "tags": [
      "ヘアサロン",
      "日本人スタイリスト",
      "ハンブルク",
      "ネイル",
      "マッサージ"
    ],
    "hours": "月〜金 10:00-19:00 / 土 10:00-18:00",
    "last_verified": "2026-04-07",
    "status": "unverified",
    "source": "web_search",
    "place_id": "",
    "priority": 4,
    "ai_reviewed": true,
    "place_reviewed": true,
    "japanese_staff": true,
    "rating": null,
    "user_rating_count": null,
    "price_level": null,
    "photo_name": null
  },
  {
    "slug": "iramasure-berlin-schoneberg",
    "name": "iramasure (Schöneberg)",
    "name_ja": "イラマシュレ（シェーネベルク）",
    "area": "Berlin, Schöneberg",
    "address": "Winterfeldtstraße 13, 10781 Berlin",
    "lat": 52.4973,
    "lng": 13.3548,
    "phone": "+493034503066",
    "phone_local": "030 34503066",
    "email": null,
    "website": "https://www.iramasure.com",
    "description": "ベルリン・シェーネベルクの日本人スタイリスト美容室。パーマ・縮毛矯正・カラー・ヘッドスパなど日本式施術に加えまつ毛エクステも提供。3店舗展開の人気サロン。",
    "detail": "ベルリンに3店舗を展開する日本人経営ヘアサロン「iramasure」のシェーネベルク店（Winterfeldtstraße 13）。パーマ・縮毛矯正・カラーリング・ヘッドスパ・まつ毛エクステ・レーザー脱毛まで幅広い美容サービスを日本語で提供。Kreuzberg（Riemannstraße 16）とFriedrichshain（Gärtnerstraße 11）にも姉妹店あり。火〜土営業、月日定休。",
    "tags": [
      "ヘアサロン",
      "日本人経営",
      "縮毛矯正",
      "まつ毛エクステ",
      "ベルリン"
    ],
    "hours": "closed / 11:00-20:00 / 11:00-20:00 / 11:00-20:00 / 11:00-20:00 / 10:00-18:00 / closed",
    "last_verified": "2026-04-07",
    "status": "unverified",
    "source": "web_search",
    "place_id": "",
    "priority": 5,
    "ai_reviewed": true,
    "place_reviewed": true,
    "japanese_staff": true,
    "rating": null,
    "user_rating_count": null,
    "price_level": null,
    "photo_name": null
  },
  {
    "slug": "iramasure-berlin-kreuzberg",
    "name": "iramasure (Kreuzberg)",
    "name_ja": "イラマシュレ（クロイツベルク）",
    "area": "Berlin, Kreuzberg",
    "address": "Riemannstrasse 16, 10961 Berlin",
    "lat": 52.4892,
    "lng": 13.3907,
    "phone": "+4915785153735",
    "phone_local": "0157 85153735",
    "email": null,
    "website": "https://www.iramasure.com",
    "description": "ベルリン・クロイツベルクの日本人スタイリスト美容室。縮毛矯正・パーマ・カラーが得意で自然な仕上がりが評判。iramasure3店舗のひとつ。",
    "detail": "ベルリン3店舗展開の日本人経営ヘアサロン「iramasure」のクロイツベルク店（Riemannstraße 16）。縮毛矯正・パーマ・カラーリングを得意とし、自然で仕上がりの美しいスタイルが評判。火〜土営業（火〜金10:00-19:00、土10:00-18:00）。月日定休。シェーネベルク（Winterfeldtstraße 13）とFriedrichshain（Gärtnerstraße 11）にも拠点あり。",
    "tags": [
      "ヘアサロン",
      "日本人経営",
      "縮毛矯正",
      "パーマ",
      "ベルリン"
    ],
    "hours": "closed / 10:00-19:00 / 10:00-19:00 / 10:00-19:00 / 10:00-19:00 / 10:00-18:00 / closed",
    "last_verified": "2026-04-07",
    "status": "unverified",
    "source": "web_search",
    "place_id": "",
    "priority": 4,
    "ai_reviewed": true,
    "place_reviewed": true,
    "japanese_staff": true,
    "rating": null,
    "user_rating_count": null,
    "price_level": null,
    "photo_name": null
  },
  {
    "slug": "iramasure-berlin-friedrichshain",
    "name": "iramasure (Friedrichshain)",
    "name_ja": "イラマシュレ（フリードリヒスハイン）",
    "area": "Berlin, Friedrichshain",
    "address": "Gärtnerstrasse 11, 10245 Berlin",
    "lat": 52.5103,
    "lng": 13.4543,
    "phone": "+493097002670",
    "phone_local": "030 97002670",
    "email": null,
    "website": "https://www.iramasure.com",
    "description": "ベルリン・フリードリヒスハインの日本人スタイリスト美容室。iramasure3店舗目として地域の日本人に親しまれ、縮毛矯正・パーマ・カラーを日本語で提供。",
    "detail": "ベルリン3店舗展開の日本人経営ヘアサロン「iramasure」のフリードリヒスハイン店（Gärtnerstraße 11）。縮毛矯正・パーマ・カラーリングを主力サービスとし、日本語でのカウンセリングが可能。火〜土営業（火〜金10:30-19:30、土10:00-18:00）。月日定休。シェーネベルク（Winterfeldtstraße 13）とKreuzberg（Riemannstraße 16）にも姉妹店あり。",
    "tags": [
      "ヘアサロン",
      "日本人経営",
      "縮毛矯正",
      "パーマ",
      "ベルリン"
    ],
    "hours": "closed / 10:30-19:30 / 10:30-19:30 / 10:30-19:30 / 10:30-19:30 / 10:00-18:00 / closed",
    "last_verified": "2026-04-07",
    "status": "unverified",
    "source": "web_search",
    "place_id": "",
    "priority": 4,
    "ai_reviewed": true,
    "place_reviewed": true,
    "japanese_staff": true,
    "rating": null,
    "user_rating_count": null,
    "price_level": null,
    "photo_name": null
  },
  {
    "slug": "nina-hair-salon-berlin",
    "name": "NINA Hair Salon",
    "name_ja": "ニナ ヘアサロン",
    "area": "Berlin, Charlottenburg",
    "address": "Leibnizstraße 20, 10625 Berlin",
    "lat": null,
    "lng": null,
    "phone": null,
    "phone_local": null,
    "email": "booking@nina-salon.com",
    "website": "https://nina-salon.com/",
    "description": "ドイツ最高評価の日本人・アジア系ヘアサロン。Googleで600件超の高評価レビューを持ち、100%日本人スタイリストが完全マンツーマンで担当する予約制サロン。",
    "detail": "ベルリン・シャルロッテンブルクに位置するドイツ最高評価の日本人・アジア系ヘアサロン。Googleで600件以上の5つ星レビューを獲得。スタッフ全員が日本人スタイリストで、アジア系・ヨーロッパ系両方の髪質に精通。完全マンツーマン制・完全予約制でウォークインは不可。カットは€75〜。縮毛矯正・デジタルパーマ・カラー・日本式超音波トリートメントに対応。予約・問い合わせはInstagram(@nina.hairsalon)またはbooking@nina-salon.comにて受付。",
    "tags": [
      "日系美容院",
      "ヘアサロン",
      "日本人スタイリスト",
      "高評価",
      "ベルリン"
    ],
    "hours": "月〜土 9:00-19:00",
    "last_verified": "2026-04-07",
    "status": "unverified",
    "source": "web_search",
    "place_id": "",
    "priority": 8,
    "ai_reviewed": true,
    "place_reviewed": true,
    "japanese_staff": true,
    "rating": null,
    "user_rating_count": null,
    "price_level": null,
    "photo_name": null
  },
  {
    "slug": "rinas-selection",
    "name": "Rina's Selection Total Beauty Lounge",
    "name_ja": "リナズセレクション",
    "area": "Düsseldorf, Oberkassel",
    "address": "Quirinstraße 3, 40545 Düsseldorf",
    "lat": null,
    "lng": null,
    "phone": null,
    "phone_local": null,
    "email": null,
    "website": "https://www.rinasele.com",
    "description": "2013年開業・日本人オーナー経営のデュッセルドルフ美容サロン。ハイドラフェイシャル・まつ毛エクステ・フォトフェイシャル・レーザー脱毛など日本式の美容トリートメントに特化。",
    "detail": "2013年5月に開業した日本人オーナー経営の美容サロン。オーナーは2011〜12年に日本で美容トレーニングを受け、2012年に渡独後にホームサロンを経て2017〜18年にオーバーカッセルのBelsenplatzへ移転。ハイドラフェイシャル・フォトフェイシャル（光治療）・まつ毛エクステ・まつ毛パーマ・スキンケア・レーザー脱毛を提供。子連れ可能な無料託児サービスも対応。デュッセルドルフ在住の日本人女性から圧倒的な人気を誇る。",
    "tags": [
      "エステ",
      "まつ毛エクステ",
      "脱毛",
      "日本人経営",
      "デュッセルドルフ"
    ],
    "hours": null,
    "last_verified": "2026-04-07",
    "status": "unverified",
    "source": "web_search",
    "place_id": "",
    "priority": 5,
    "ai_reviewed": true,
    "place_reviewed": true,
    "japanese_staff": true,
    "rating": null,
    "user_rating_count": null,
    "price_level": null,
    "photo_name": null
  },
  {
    "slug": "salon-ichigo",
    "name": "Salon Ichigo",
    "name_ja": "サロン一期",
    "area": "Düsseldorf, Heerdt",
    "address": "Willstätterstraße 73, 40549 Düsseldorf",
    "lat": null,
    "lng": null,
    "phone": "+492114165569",
    "phone_local": "0211 4165569",
    "email": "salon.ichigo.dus@gmail.com",
    "website": "https://www.salon-ichigo.tokyo",
    "description": "デュッセルドルフ・ヒアートの日本人スタイリストサロン。東京で15年以上のキャリアを持つKaoriとYusukeが日本語・英語・ドイツ語で対応。高品質な日本製品を使用。",
    "detail": "デュッセルドルフ・ヒアートに位置する日本人スタイリストによるヘアサロン。スタイリストのKaoriとYusukeは、東京の有名トータルビューティーサロンで経験を積んだ後、Salon Ichigo（2019年参加）で15年以上の実績を持つ。カット・カラー・ハイライト・バレイヤージュ・ヘッドスパ対応。高品質な日本製ヘアケア製品を使用。日本語・英語・ドイツ語での相談が可能。",
    "tags": [
      "ヘアサロン",
      "日本人スタイリスト",
      "日本語対応",
      "カラー",
      "デュッセルドルフ"
    ],
    "hours": "月〜金 10:00-18:00 / 土 9:00-17:00",
    "last_verified": "2026-04-07",
    "status": "unverified",
    "source": "web_search",
    "place_id": "",
    "priority": 5,
    "ai_reviewed": true,
    "place_reviewed": true,
    "japanese_staff": true,
    "rating": null,
    "user_rating_count": null,
    "price_level": null,
    "photo_name": null
  },
  {
    "slug": "salon-mai-dusseldorf",
    "name": "Salon MAI",
    "name_ja": "サロン・マイ",
    "area": "Düsseldorf, Stadt-Mitte",
    "address": "Kreuzstraße 26, 40210 Düsseldorf",
    "lat": 51.2188,
    "lng": 6.7876,
    "phone": "+492113248440",
    "phone_local": "0211 324844",
    "email": "appointment@salon-mai.de",
    "website": "https://salon-mai.com",
    "description": "1977年創業・ドイツ初の公認日本人ヘアサロン。アジア系の髪質に精通した日本人スタイリストが縮毛矯正・ヘッドスパなどの日本式ケアを提供し、在独日本人から長年の信頼を獲得。",
    "detail": "1977年に開業した「ドイツ初の公認日本人ヘアサロン」として知られるデュッセルドルフの老舗。日本人スタイリストが縮毛矯正・ヘッドスパ・カット・カラー・パーマを提供。日本ブランドMILBONの製品を使用した高品質なヘアケアが特徴。日本人だけでなく現地在住者・国際顧客にも長年サービスを提供し、デュッセルドルフの日本人コミュニティで最も歴史あるサロンのひとつ。月〜金10:00-20:00、土9:00-18:00営業。",
    "tags": [
      "ヘアサロン",
      "老舗",
      "日本人スタイリスト",
      "縮毛矯正",
      "デュッセルドルフ"
    ],
    "hours": "10:00-20:00 / 10:00-20:00 / 10:00-20:00 / 10:00-20:00 / 10:00-20:00 / 09:00-18:00 / closed",
    "last_verified": "2026-04-07",
    "status": "unverified",
    "source": "web_search",
    "place_id": null,
    "priority": 8,
    "ai_reviewed": true,
    "place_reviewed": true,
    "japanese_staff": true,
    "rating": null,
    "user_rating_count": null,
    "price_level": null,
    "photo_name": null
  },
  {
    "slug": "salon-yoda",
    "name": "Salon YŌDA",
    "name_ja": "サロン ヨーダ",
    "area": "Düsseldorf, Stadt-Mitte",
    "address": "Stresemannstraße 28, 40210 Düsseldorf",
    "lat": null,
    "lng": null,
    "phone": "+491624044181",
    "phone_local": "0162 4044181",
    "email": "contact@yoda-hair.com",
    "website": "https://yoda-hair.com",
    "description": "日本人オーナー・与田和典氏が運営するデュッセルドルフのヘアサロン。アート・ファッション・音楽を融合したユニークな空間で、ギャラリー展示も開催。完全予約制。",
    "detail": "福井県出身の日本人スタイリスト・与田和典氏がニューヨーク（ブルックリン）での3年間を経て、デュッセルドルフに開業した個性派ヘアサロン。ヘアスタイルにアート・ファッション・音楽を融合させた独自の空間を持ち、年5回のアート展示も開催。オリジナルアパレルブランド「YŌDA wear」も展開。少人数制・完全予約制で、丁寧な施術が評判。火〜土10:00-20:00営業。",
    "tags": [
      "ヘアサロン",
      "日本人オーナー",
      "完全予約制",
      "アート",
      "デュッセルドルフ"
    ],
    "hours": "火〜土 10:00-20:00",
    "last_verified": "2026-04-07",
    "status": "unverified",
    "source": "web_search",
    "place_id": "",
    "priority": 4,
    "ai_reviewed": true,
    "place_reviewed": true,
    "japanese_staff": true,
    "rating": null,
    "user_rating_count": null,
    "price_level": null,
    "photo_name": null
  },
  {
    "slug": "salon-mocci-munich",
    "name": "salon mocci",
    "name_ja": "サロン モッチ",
    "area": "München, Altstadt",
    "address": "Westenriederstraße 15, 80331 München",
    "lat": 48.1349,
    "lng": 11.5786,
    "phone": "+498921028371",
    "phone_local": "089 21028371",
    "email": "info@salon-mocci.com",
    "website": "https://www.salon-mocci.com",
    "description": "2013年創業のミュンヘン旧市街の日本人スタイリスト美容室。太い髪質に精通したKarino Motoyuki氏が率いるチームが日本語で丁寧に施術。",
    "detail": "2013年にKarino Motoyuki氏が開業したミュンヘン旧市街のヘアサロン。日本人スタイリストが在籍し、アジア系の太い髪質を得意とする技術が定評。カット・カラー・縮毛矯正（日本式ストレートパーマ）など幅広いサービスを日本語・英語・ドイツ語で提供。火〜金10:00-18:00、土9:00-17:00営業。",
    "tags": [
      "ヘアサロン",
      "日本人スタイリスト",
      "縮毛矯正",
      "ミュンヘン"
    ],
    "hours": "火〜金 10:00-18:00 / 土 09:00-17:00",
    "last_verified": "2026-04-07",
    "status": "unverified",
    "source": "web_search",
    "place_id": "",
    "priority": 5,
    "ai_reviewed": true,
    "place_reviewed": true,
    "japanese_staff": true,
    "rating": null,
    "user_rating_count": null,
    "price_level": null,
    "photo_name": null
  },
  {
    "slug": "hairsalon-club-ys-dusseldorf",
    "name": "Hairsalon Club Y's",
    "name_ja": "ヘアサロン クラブワイズ",
    "area": "Düsseldorf, Stadtmitte",
    "address": "Charlottenstraße 55, 40210 Düsseldorf",
    "phone": "+4921116 2617",
    "phone_local": null,
    "email": "clubys194@gmail.com",
    "website": null,
    "description": "デュッセルドルフ中心部の日本スタイルヘアサロン。全スタイリストが日本でのトレーニング経験を持ち、縮毛矯正・ナチュラルカラーなどの日本式ヘアケアを月〜金夜8時まで提供。",
    "detail": "デュッセルドルフ・シャルロッテン通りに位置する日本スタイルの美容院。全スタイリストが日本でのトレーニング経験を持ち、縮毛矯正・ナチュラルカラー・各種トリートメント・マッサージサービスを提供。月〜金10:00-20:00と夜遅くまで営業する利便性の高いサロン。",
    "tags": [
      "日本人美容師",
      "ヘアサロン",
      "縮毛矯正",
      "デュッセルドルフ"
    ],
    "hours": "月〜金 10:00-20:00 / 土 10:00-18:00",
    "last_verified": "2026-04-07",
    "status": "unverified",
    "source": "web_search",
    "place_id": "",
    "priority": 3,
    "ai_reviewed": true,
    "place_reviewed": true,
    "japanese_staff": true,
    "rating": null,
    "user_rating_count": null,
    "price_level": null,
    "photo_name": null
  },
  {
    "slug": "atelier-ichie-dusseldorf",
    "name": "atelier ICHIE",
    "name_ja": "アトリエ イチエ",
    "area": "Düsseldorf, Stadtmitte",
    "address": "Hohenzollernstraße 15, 40211 Düsseldorf",
    "phone": "+4921117938090",
    "phone_local": "0211 17938090",
    "email": "atelier.ichie.dus@gmail.com",
    "website": "https://en.atelier-ichie.tokyo/",
    "description": "デュッセルドルフの日本式ヘアサロン。東京・大阪にも姉妹店を持ち、精密な日本スタイルカット・カラー・まつ毛エクステ・ネイルを日本語で提供。個別スタイルコンサル付き。",
    "detail": "東京・大阪に姉妹店を持つ日本式ヘアサロンのデュッセルドルフ店。スタイリストは2013年から東京で美容師としてキャリアを積み、2017年にパーマ部門で賞を受賞したのち渡独。精密なカット技術・繊細なカラーリング・個別スタイルコンサルティングが特徴。まつ毛エクステ・ネイルサービスも提供。日本語・英語・ドイツ語での相談が可能。月〜金10:00-20:00、土10:00-18:00営業。",
    "tags": [
      "日本人美容師",
      "ヘアサロン",
      "まつ毛エクステ",
      "ネイル",
      "デュッセルドルフ"
    ],
    "hours": "月〜金 10:00-20:00 / 土 10:00-18:00",
    "last_verified": "2026-04-07",
    "status": "unverified",
    "source": "web_search",
    "place_id": "",
    "priority": 5,
    "ai_reviewed": true,
    "place_reviewed": true,
    "japanese_staff": true,
    "rating": null,
    "user_rating_count": null,
    "price_level": null,
    "photo_name": null
  },
  {
    "slug": "friseur-shingo-berlin",
    "name": "FRISEUR SHINGO",
    "name_ja": "フリズール シンゴ",
    "area": "Berlin, Charlottenburg-Wilmersdorf",
    "address": "Bundesallee 48A, 10715 Berlin",
    "phone": "+493086395787",
    "phone_local": "030 86395787",
    "email": "info@friseurshingo.net",
    "website": "https://friseurshingo.net",
    "source_url": "https://friseurshingo.net/impressum-privacy-policy/",
    "description": "2020年開業のベルリン・シャルロッテンブルクの日本人経営ヘアサロン。カット・カラー・パーマ・縮毛矯正・まつ毛・ブロウサービスに加えマッサージも提供。日独英対応。",
    "tags": [
      "ヘアサロン",
      "日本人経営",
      "縮毛矯正",
      "まつ毛エクステ",
      "ベルリン"
    ],
    "hours": "火〜金 10:00-19:00 / 土 10:00-18:00",
    "status": "unverified",
    "last_verified": "2026-04-17",
    "source": "website",
    "ai_reviewed": true,
    "place_id": "",
    "priority": 5,
    "japanese_staff": true,
    "rating": null,
    "user_rating_count": null,
    "price_level": null,
    "photo_name": null
  },
  {
    "slug": "sakai-hair-berlin",
    "name": "SAKAI",
    "name_ja": "サカイ",
    "area": "Berlin, Friedrichshain",
    "address": "Weichselstraße 35, 10247 Berlin",
    "phone": "+493043962926",
    "phone_local": "030 43962926",
    "email": "hi.sakaihairberlin@gmail.com",
    "website": "https://sakaihairberlin.com",
    "source_url": "https://sakaihairberlin.com/privacy-policy-impressum",
    "description": "ベルリン・フリードリヒスハインの日本人スタイリスト（Atsuko）が2023年に開業したヘアサロン。東京・NY・ベルリンでのキャリアを持ち、バレイヤージュ・ハイライト・カットに対応。",
    "tags": [
      "ヘアサロン",
      "日本人スタイリスト",
      "バレイヤージュ",
      "カラー",
      "ベルリン"
    ],
    "hours": null,
    "status": "unverified",
    "last_verified": "2026-04-17",
    "source": "website",
    "ai_reviewed": true,
    "place_id": "",
    "priority": 4,
    "japanese_staff": true,
    "rating": null,
    "user_rating_count": null,
    "price_level": null,
    "photo_name": null
  },
  {
    "slug": "hoshi-coupe-berlin",
    "name": "HOSHI COUPE Berlin",
    "name_ja": "ホシクープ ベルリン",
    "area": "Berlin, Mitte",
    "address": "Garnisonkirchplatz 2, 10178 Berlin",
    "phone": "+493027891720",
    "phone_local": "030 27891720",
    "email": null,
    "website": "https://www.hoshicoupe.com",
    "source_url": "https://www.yelp.com/biz/hoshi-coupe-berlin-berlin-3",
    "description": "ベルリン・ミッテのハッケシャー・マルクト近くにある日本人スタッフのヘアサロン。NY・パリ・京都にも展開する日系サロンで、シアツーヘッドマッサージも提供。",
    "tags": [
      "ヘアサロン",
      "日本人スタッフ",
      "シアツーマッサージ",
      "ベルリン",
      "ミッテ"
    ],
    "hours": "月〜日 11:00-19:00",
    "status": "unverified",
    "last_verified": "2026-04-17",
    "source": "google_maps",
    "ai_reviewed": true,
    "place_id": "",
    "priority": 5,
    "japanese_staff": true,
    "rating": null,
    "user_rating_count": null,
    "price_level": null,
    "photo_name": null
  }
]
